{"nodes":[{"cover":0,"min_v":0.0167,"max_v":0.1198,"avg_v":0.0803,"comp_len":20,"x":265.625,"y":222.9367,"id":"mn0"},{"cover":0,"min_v":0.0049,"max_v":0.1247,"avg_v":0.075,"comp_len":19,"x":265.625,"y":277.0633,"id":"mn1"},{"cover":0,"min_v":0.0,"max_v":0.1239,"avg_v":0.0782,"comp_len":17,"x":250.0,"y":250.0,"id":"mn2"},{"cover":0,"min_v":0.041,"max_v":0.1206,"avg_v":0.0845,"comp_len":6,"x":233.7205,"y":157.6743,"id":"mn3"},{"cover":1,"min_v":0.1259,"max_v":0.2405,"avg_v":0.172,"comp_len":27,"x":239.147,"y":188.4495,"id":"mn4"},{"cover":1,"min_v":0.1275,"max_v":0.2136,"avg_v":0.171,"comp_len":20,"x":304.1266,"y":281.25,"id":"mn5"},{"cover":1,"min_v":0.1369,"max_v":0.2449,"avg_v":0.1786,"comp_len":17,"x":218.75,"y":250.0,"id":"mn6"},{"cover":1,"min_v":0.1434,"max_v":0.2474,"avg_v":0.1954,"comp_len":13,"x":187.5,"y":250.0,"id":"mn7"},{"cover":1,"min_v":0.1552,"max_v":0.2327,"avg_v":0.1945,"comp_len":10,"x":281.25,"y":195.8734,"id":"mn8"},{"cover":1,"min_v":0.1296,"max_v":0.1296,"avg_v":0.1296,"comp_len":1,"x":235.4884,"y":125.8452,"id":"mn9"},{"cover":2,"min_v":0.2526,"max_v":0.3367,"avg_v":0.2965,"comp_len":9,"x":157.6743,"y":266.2795,"id":"mn10"},{"cover":2,"min_v":0.2689,"max_v":0.3611,"avg_v":0.3143,"comp_len":9,"x":282.0644,"y":161.9038,"id":"mn11"},{"cover":2,"min_v":0.2506,"max_v":0.2961,"avg_v":0.2732,"comp_len":3,"x":202.1222,"y":209.8258,"id":"mn12"},{"cover":2,"min_v":0.2551,"max_v":0.2673,"avg_v":0.2612,"comp_len":2,"x":255.4511,"y":156.4086,"id":"mn13"},{"cover":3,"min_v":0.405,"max_v":0.4984,"avg_v":0.4576,"comp_len":11,"x":302.8273,"y":136.7115,"id":"mn14"},{"cover":3,"min_v":0.3875,"max_v":0.489,"avg_v":0.4382,"comp_len":11,"x":125.4757,"y":260.8945,"id":"mn15"},{"cover":4,"min_v":0.5422,"max_v":0.5686,"avg_v":0.5547,"comp_len":5,"x":93.8987,"y":256.8155,"id":"mn16"},{"cover":4,"min_v":0.5032,"max_v":0.5682,"avg_v":0.5489,"comp_len":4,"x":316.0341,"y":108.3894,"id":"mn17"},{"cover":4,"min_v":0.563,"max_v":0.5784,"avg_v":0.5683,"comp_len":3,"x":324.1563,"y":112.4685,"id":"mn18"},{"cover":5,"min_v":0.6271,"max_v":0.7449,"avg_v":0.6871,"comp_len":10,"x":62.5446,"y":254.0903,"id":"mn19"},{"cover":5,"min_v":0.6454,"max_v":0.74,"avg_v":0.7012,"comp_len":10,"x":341.3784,"y":86.2739,"id":"mn20"},{"cover":6,"min_v":0.8058,"max_v":0.8367,"avg_v":0.8195,"comp_len":5,"x":31.263,"y":252.3861,"id":"mn21"},{"cover":6,"min_v":0.8241,"max_v":0.8323,"avg_v":0.8282,"comp_len":5,"x":354.7511,"y":57.9615,"id":"mn22"},{"cover":6,"min_v":0.8266,"max_v":0.8363,"avg_v":0.8324,"comp_len":3,"x":358.4553,"y":60.0289,"id":"mn23"},{"cover":7,"min_v":0.9017,"max_v":1.0,"avg_v":0.9262,"comp_len":7,"x":0.0335,"y":254.0904,"id":"mn24"},{"cover":7,"min_v":0.9204,"max_v":0.9297,"avg_v":0.9248,"comp_len":5,"x":370.2472,"y":30.8183,"id":"mn25"}],"links":[{"value":5,"source":"mn0","target":"mn2"},{"value":18,"source":"mn0","target":"mn4"},{"value":4,"source":"mn0","target":"mn3"},{"value":8,"source":"mn0","target":"mn8"},{"value":10,"source":"mn1","target":"mn2"},{"value":16,"source":"mn1","target":"mn5"},{"value":4,"source":"mn1","target":"mn7"},{"value":3,"source":"mn1","target":"mn6"},{"value":4,"source":"mn1","target":"mn3"},{"value":10,"source":"mn2","target":"mn6"},{"value":2,"source":"mn2","target":"mn3"},{"value":4,"source":"mn2","target":"mn4"},{"value":6,"source":"mn2","target":"mn5"},{"value":9,"source":"mn3","target":"mn4"},{"value":4,"source":"mn3","target":"mn9"},{"value":8,"source":"mn4","target":"mn13"},{"value":3,"source":"mn4","target":"mn8"},{"value":7,"source":"mn5","target":"mn6"},{"value":3,"source":"mn5","target":"mn7"},{"value":4,"source":"mn5","target":"mn12"},{"value":8,"source":"mn6","target":"mn7"},{"value":6,"source":"mn6","target":"mn12"},{"value":12,"source":"mn7","target":"mn10"},{"value":9,"source":"mn8","target":"mn11"},{"value":10,"source":"mn10","target":"mn15"},{"value":9,"source":"mn11","target":"mn14"},{"value":5,"source":"mn14","target":"mn18"},{"value":8,"source":"mn14","target":"mn17"},{"value":10,"source":"mn15","target":"mn16"},{"value":9,"source":"mn16","target":"mn19"},{"value":2,"source":"mn17","target":"mn18"},{"value":4,"source":"mn17","target":"mn20"},{"value":5,"source":"mn18","target":"mn20"},{"value":9,"source":"mn19","target":"mn21"},{"value":9,"source":"mn20","target":"mn22"},{"value":4,"source":"mn20","target":"mn23"},{"value":11,"source":"mn21","target":"mn24"},{"value":7,"source":"mn22","target":"mn25"},{"value":3,"source":"mn22","target":"mn23"},{"value":3,"source":"mn23","target":"mn25"}],"info":{"component_method":"modularity","link_method":"connectivity","cover_overlap":0.0,"cover_intervals":8,"cover":[{"level":0,"range":[0.0,0.125]},{"level":1,"range":[0.125,0.25]},{"level":2,"range":[0.25,0.375]},{"level":3,"range":[0.375,0.5]},{"level":4,"range":[0.5,0.625]},{"level":5,"range":[0.625,0.75]},{"level":6,"range":[0.75,0.875]},{"level":7,"range":[0.875,1.0]}],"compute_time":0.0836}}