{"nodes":[{"cover":0,"min_v":0.0558,"max_v":0.0558,"avg_v":0.0558,"comp_len":1,"x":307.6374,"y":247.4835,"id":"mn0"},{"cover":0,"min_v":0.0757,"max_v":0.0757,"avg_v":0.0757,"comp_len":1,"x":262.4869,"y":193.6752,"id":"mn1"},{"cover":0,"min_v":0.008,"max_v":0.0996,"avg_v":0.0438,"comp_len":3,"x":434.5073,"y":146.5323,"id":"mn2"},{"cover":0,"min_v":0.0518,"max_v":0.0518,"avg_v":0.0518,"comp_len":1,"x":441.7772,"y":160.7249,"id":"mn3"},{"cover":0,"min_v":0.0279,"max_v":0.0279,"avg_v":0.0279,"comp_len":1,"x":389.5382,"y":185.21,"id":"mn4"},{"cover":0,"min_v":0.0876,"max_v":0.0876,"avg_v":0.0876,"comp_len":1,"x":354.6359,"y":201.3695,"id":"mn5"},{"cover":0,"min_v":0.0,"max_v":0.0956,"avg_v":0.0372,"comp_len":3,"x":390.6681,"y":187.7014,"id":"mn6"},{"cover":0,"min_v":0.012,"max_v":0.0916,"avg_v":0.0428,"comp_len":4,"x":402.0647,"y":423.5822,"id":"mn7"},{"cover":0,"min_v":0.0199,"max_v":0.0199,"avg_v":0.0199,"comp_len":1,"x":274.7261,"y":177.1592,"id":"mn8"},{"cover":0,"min_v":0.0677,"max_v":0.0677,"avg_v":0.0677,"comp_len":1,"x":367.1271,"y":183.6483,"id":"mn9"},{"cover":0,"min_v":0.0398,"max_v":0.0398,"avg_v":0.0398,"comp_len":1,"x":406.9107,"y":176.9612,"id":"mn10"},{"cover":0,"min_v":0.0598,"max_v":0.0598,"avg_v":0.0598,"comp_len":1,"x":338.0459,"y":211.3544,"id":"mn11"},{"cover":0,"min_v":0.0837,"max_v":0.0837,"avg_v":0.0837,"comp_len":1,"x":338.116,"y":211.5145,"id":"mn12"},{"cover":0,"min_v":0.0797,"max_v":0.0797,"avg_v":0.0797,"comp_len":1,"x":338.1858,"y":211.6748,"id":"mn13"},{"cover":0,"min_v":0.0717,"max_v":0.0717,"avg_v":0.0717,"comp_len":1,"x":355.2506,"y":202.7146,"id":"mn14"},{"cover":0,"min_v":0.0637,"max_v":0.0637,"avg_v":0.0637,"comp_len":1,"x":354.6183,"y":201.3314,"id":"mn15"},{"cover":0,"min_v":0.0438,"max_v":0.0438,"avg_v":0.0438,"comp_len":1,"x":441.7773,"y":160.7251,"id":"mn16"},{"cover":0,"min_v":0.004,"max_v":0.004,"avg_v":0.004,"comp_len":1,"x":406.9791,"y":177.1084,"id":"mn17"},{"cover":0,"min_v":0.0478,"max_v":0.0478,"avg_v":0.0478,"comp_len":1,"x":434.5034,"y":146.5253,"id":"mn18"},{"cover":1,"min_v":0.1633,"max_v":0.1713,"avg_v":0.1673,"comp_len":2,"x":373.0915,"y":195.5042,"id":"mn19"},{"cover":1,"min_v":0.1753,"max_v":0.1753,"avg_v":0.1753,"comp_len":1,"x":254.8234,"y":134.7162,"id":"mn20"},{"cover":1,"min_v":0.1594,"max_v":0.1912,"avg_v":0.1753,"comp_len":2,"x":376.6658,"y":394.6998,"id":"mn21"},{"cover":1,"min_v":0.1036,"max_v":0.1514,"avg_v":0.1225,"comp_len":4,"x":373.086,"y":195.4918,"id":"mn22"},{"cover":1,"min_v":0.1793,"max_v":0.1793,"avg_v":0.1793,"comp_len":1,"x":267.3484,"y":194.9779,"id":"mn23"},{"cover":1,"min_v":0.1275,"max_v":0.1992,"avg_v":0.1607,"comp_len":3,"x":406.9087,"y":176.957,"id":"mn24"},{"cover":1,"min_v":0.1952,"max_v":0.1952,"avg_v":0.1952,"comp_len":1,"x":373.108,"y":195.5415,"id":"mn25"},{"cover":1,"min_v":0.1394,"max_v":0.1394,"avg_v":0.1394,"comp_len":1,"x":414.7368,"y":438.0473,"id":"mn26"},{"cover":1,"min_v":0.1434,"max_v":0.1673,"avg_v":0.1553,"comp_len":2,"x":253.9849,"y":134.6842,"id":"mn27"},{"cover":1,"min_v":0.1235,"max_v":0.1315,"avg_v":0.1275,"comp_len":2,"x":451.2821,"y":137.1287,"id":"mn28"},{"cover":1,"min_v":0.1076,"max_v":0.1116,"avg_v":0.1096,"comp_len":2,"x":389.5366,"y":185.2067,"id":"mn29"},{"cover":1,"min_v":0.1873,"max_v":0.1873,"avg_v":0.1873,"comp_len":1,"x":329.79,"y":333.3497,"id":"mn30"},{"cover":1,"min_v":0.1355,"max_v":0.1355,"avg_v":0.1355,"comp_len":1,"x":389.5397,"y":185.2134,"id":"mn31"},{"cover":1,"min_v":0.1474,"max_v":0.1833,"avg_v":0.1653,"comp_len":2,"x":254.1934,"y":173.1913,"id":"mn32"},{"cover":2,"min_v":0.2709,"max_v":0.2709,"avg_v":0.2709,"comp_len":1,"x":389.26,"y":409.2331,"id":"mn33"},{"cover":2,"min_v":0.247,"max_v":0.247,"avg_v":0.247,"comp_len":1,"x":255.7903,"y":115.5092,"id":"mn34"},{"cover":2,"min_v":0.251,"max_v":0.2908,"avg_v":0.2709,"comp_len":2,"x":333.7911,"y":202.8343,"id":"mn35"},{"cover":2,"min_v":0.239,"max_v":0.239,"avg_v":0.239,"comp_len":1,"x":389.4727,"y":185.0691,"id":"mn36"},{"cover":2,"min_v":0.243,"max_v":0.243,"avg_v":0.243,"comp_len":1,"x":417.7428,"y":155.9543,"id":"mn37"},{"cover":2,"min_v":0.2032,"max_v":0.2032,"avg_v":0.2032,"comp_len":1,"x":372.089,"y":193.294,"id":"mn38"},{"cover":2,"min_v":0.2231,"max_v":0.2231,"avg_v":0.2231,"comp_len":1,"x":326.0784,"y":336.7507,"id":"mn39"},{"cover":2,"min_v":0.2112,"max_v":0.2629,"avg_v":0.2371,"comp_len":2,"x":277.1964,"y":277.1964,"id":"mn40"},{"cover":2,"min_v":0.2988,"max_v":0.2988,"avg_v":0.2988,"comp_len":1,"x":257.2468,"y":115.5798,"id":"mn41"},{"cover":2,"min_v":0.2669,"max_v":0.2669,"avg_v":0.2669,"comp_len":1,"x":355.1645,"y":202.5233,"id":"mn42"},{"cover":2,"min_v":0.2191,"max_v":0.2191,"avg_v":0.2191,"comp_len":1,"x":254.7102,"y":115.467,"id":"mn43"},{"cover":2,"min_v":0.2948,"max_v":0.2948,"avg_v":0.2948,"comp_len":1,"x":256.0271,"y":154.0352,"id":"mn44"},{"cover":2,"min_v":0.2749,"max_v":0.2749,"avg_v":0.2749,"comp_len":1,"x":351.0166,"y":366.0357,"id":"mn45"},{"cover":2,"min_v":0.2151,"max_v":0.2829,"avg_v":0.249,"comp_len":2,"x":384.1686,"y":174.7177,"id":"mn46"},{"cover":2,"min_v":0.255,"max_v":0.255,"avg_v":0.255,"comp_len":1,"x":254.8325,"y":115.4714,"id":"mn47"},{"cover":2,"min_v":0.2271,"max_v":0.2271,"avg_v":0.2271,"comp_len":1,"x":254.9799,"y":153.9752,"id":"mn48"},{"cover":2,"min_v":0.259,"max_v":0.259,"avg_v":0.259,"comp_len":1,"x":390.676,"y":187.7191,"id":"mn49"},{"cover":2,"min_v":0.2311,"max_v":0.2311,"avg_v":0.2311,"comp_len":1,"x":280.9076,"y":158.949,"id":"mn50"},{"cover":2,"min_v":0.2072,"max_v":0.2072,"avg_v":0.2072,"comp_len":1,"x":424.3434,"y":168.842,"id":"mn51"},{"cover":2,"min_v":0.2869,"max_v":0.2869,"avg_v":0.2869,"comp_len":1,"x":354.9912,"y":202.1412,"id":"mn52"},{"cover":2,"min_v":0.2789,"max_v":0.2789,"avg_v":0.2789,"comp_len":1,"x":441.7769,"y":160.7244,"id":"mn53"},{"cover":2,"min_v":0.2351,"max_v":0.2351,"avg_v":0.2351,"comp_len":1,"x":272.0779,"y":196.6993,"id":"mn54"},{"cover":3,"min_v":0.3147,"max_v":0.3147,"avg_v":0.3147,"comp_len":1,"x":337.4018,"y":209.919,"id":"mn55"},{"cover":3,"min_v":0.3586,"max_v":0.3665,"avg_v":0.3625,"comp_len":3,"x":424.3429,"y":168.8408,"id":"mn56"},{"cover":3,"min_v":0.3307,"max_v":0.3307,"avg_v":0.3307,"comp_len":1,"x":337.4745,"y":210.0779,"id":"mn57"},{"cover":3,"min_v":0.3068,"max_v":0.3068,"avg_v":0.3068,"comp_len":1,"x":407.7508,"y":178.7939,"id":"mn58"},{"cover":3,"min_v":0.3466,"max_v":0.3984,"avg_v":0.3705,"comp_len":5,"x":372.0959,"y":193.3088,"id":"mn59"},{"cover":3,"min_v":0.3187,"max_v":0.3187,"avg_v":0.3187,"comp_len":1,"x":337.547,"y":210.237,"id":"mn60"},{"cover":3,"min_v":0.3227,"max_v":0.3227,"avg_v":0.3227,"comp_len":1,"x":276.6393,"y":198.8263,"id":"mn61"},{"cover":3,"min_v":0.3426,"max_v":0.3944,"avg_v":0.3692,"comp_len":3,"x":417.7357,"y":155.9416,"id":"mn62"},{"cover":3,"min_v":0.3108,"max_v":0.3108,"avg_v":0.3108,"comp_len":1,"x":280.9981,"y":201.3428,"id":"mn63"},{"cover":3,"min_v":0.3028,"max_v":0.3028,"avg_v":0.3028,"comp_len":1,"x":285.1209,"y":204.2296,"id":"mn64"},{"cover":3,"min_v":0.3506,"max_v":0.3506,"avg_v":0.3506,"comp_len":1,"x":414.7425,"y":438.0423,"id":"mn65"},{"cover":3,"min_v":0.3865,"max_v":0.3865,"avg_v":0.3865,"comp_len":1,"x":363.8808,"y":380.3334,"id":"mn66"},{"cover":3,"min_v":0.3825,"max_v":0.3825,"avg_v":0.3825,"comp_len":1,"x":373.097,"y":195.5167,"id":"mn67"},{"cover":3,"min_v":0.3904,"max_v":0.3904,"avg_v":0.3904,"comp_len":1,"x":253.6702,"y":153.9162,"id":"mn68"},{"cover":3,"min_v":0.3347,"max_v":0.3347,"avg_v":0.3347,"comp_len":1,"x":288.9764,"y":207.4648,"id":"mn69"},{"cover":3,"min_v":0.3267,"max_v":0.3267,"avg_v":0.3267,"comp_len":1,"x":292.5352,"y":211.0236,"id":"mn70"},{"cover":3,"min_v":0.3386,"max_v":0.3386,"avg_v":0.3386,"comp_len":1,"x":257.5304,"y":192.8013,"id":"mn71"},{"cover":4,"min_v":0.4104,"max_v":0.494,"avg_v":0.4422,"comp_len":6,"x":400.9653,"y":165.3532,"id":"mn72"},{"cover":4,"min_v":0.4821,"max_v":0.4821,"avg_v":0.4821,"comp_len":1,"x":326.9048,"y":248.3219,"id":"mn73"},{"cover":4,"min_v":0.4303,"max_v":0.4781,"avg_v":0.4542,"comp_len":2,"x":313.3986,"y":322.2923,"id":"mn74"},{"cover":4,"min_v":0.4024,"max_v":0.4462,"avg_v":0.4223,"comp_len":3,"x":389.535,"y":185.2033,"id":"mn75"},{"cover":4,"min_v":0.498,"max_v":0.498,"avg_v":0.498,"comp_len":1,"x":372.034,"y":193.1756,"id":"mn76"},{"cover":4,"min_v":0.4064,"max_v":0.4064,"avg_v":0.4064,"comp_len":1,"x":373.1025,"y":195.5291,"id":"mn77"},{"cover":4,"min_v":0.4343,"max_v":0.4701,"avg_v":0.4522,"comp_len":2,"x":252.5169,"y":173.1181,"id":"mn78"},{"cover":4,"min_v":0.4422,"max_v":0.4422,"avg_v":0.4422,"comp_len":1,"x":389.3565,"y":409.1486,"id":"mn79"},{"cover":4,"min_v":0.4382,"max_v":0.4382,"avg_v":0.4382,"comp_len":1,"x":390.6747,"y":187.7163,"id":"mn80"},{"cover":4,"min_v":0.4741,"max_v":0.4741,"avg_v":0.4741,"comp_len":1,"x":389.5323,"y":185.1974,"id":"mn81"},{"cover":4,"min_v":0.4542,"max_v":0.4542,"avg_v":0.4542,"comp_len":1,"x":390.6785,"y":187.7248,"id":"mn82"},{"cover":4,"min_v":0.4223,"max_v":0.4861,"avg_v":0.4592,"comp_len":4,"x":372.0409,"y":193.1904,"id":"mn83"},{"cover":4,"min_v":0.49,"max_v":0.49,"avg_v":0.49,"comp_len":1,"x":324.7186,"y":231.7165,"id":"mn84"},{"cover":5,"min_v":0.5179,"max_v":0.5179,"avg_v":0.5179,"comp_len":1,"x":295.7704,"y":214.8791,"id":"mn85"},{"cover":5,"min_v":0.5139,"max_v":0.5139,"avg_v":0.5139,"comp_len":1,"x":298.6572,"y":219.0019,"id":"mn86"},{"cover":5,"min_v":0.5737,"max_v":0.5857,"avg_v":0.5797,"comp_len":2,"x":250.0,"y":250.0,"id":"mn87"},{"cover":5,"min_v":0.5657,"max_v":0.5657,"avg_v":0.5657,"comp_len":1,"x":406.9769,"y":177.1037,"id":"mn88"},{"cover":5,"min_v":0.506,"max_v":0.506,"avg_v":0.506,"comp_len":1,"x":355.4857,"y":203.2414,"id":"mn89"},{"cover":5,"min_v":0.5378,"max_v":0.5498,"avg_v":0.5438,"comp_len":2,"x":337.6191,"y":210.3963,"id":"mn90"},{"cover":5,"min_v":0.5299,"max_v":0.5976,"avg_v":0.5697,"comp_len":4,"x":354.6006,"y":201.2934,"id":"mn91"},{"cover":5,"min_v":0.51,"max_v":0.51,"avg_v":0.51,"comp_len":1,"x":390.6772,"y":187.722,"id":"mn92"},{"cover":5,"min_v":0.5219,"max_v":0.5219,"avg_v":0.5219,"comp_len":1,"x":317.4405,"y":213.0009,"id":"mn93"},{"cover":5,"min_v":0.5697,"max_v":0.5697,"avg_v":0.5697,"comp_len":1,"x":255.868,"y":173.3011,"id":"mn94"},{"cover":5,"min_v":0.5339,"max_v":0.5418,"avg_v":0.5378,"comp_len":2,"x":390.2265,"y":186.7137,"id":"mn95"},{"cover":5,"min_v":0.5259,"max_v":0.5259,"avg_v":0.5259,"comp_len":1,"x":355.078,"y":202.3322,"id":"mn96"},{"cover":5,"min_v":0.5777,"max_v":0.5777,"avg_v":0.5777,"comp_len":1,"x":290.7946,"y":290.7946,"id":"mn97"},{"cover":5,"min_v":0.5817,"max_v":0.5817,"avg_v":0.5817,"comp_len":1,"x":355.5917,"y":203.4812,"id":"mn98"},{"cover":5,"min_v":0.502,"max_v":0.502,"avg_v":0.502,"comp_len":1,"x":264.9319,"y":305.7265,"id":"mn99"},{"cover":5,"min_v":0.5578,"max_v":0.5578,"avg_v":0.5578,"comp_len":1,"x":337.2767,"y":352.4894,"id":"mn100"},{"cover":5,"min_v":0.5538,"max_v":0.5538,"avg_v":0.5538,"comp_len":1,"x":406.9775,"y":177.105,"id":"mn101"},{"cover":5,"min_v":0.5458,"max_v":0.5936,"avg_v":0.5697,"comp_len":2,"x":337.691,"y":210.5556,"id":"mn102"},{"cover":6,"min_v":0.6454,"max_v":0.6693,"avg_v":0.6573,"comp_len":2,"x":301.1737,"y":223.3607,"id":"mn103"},{"cover":6,"min_v":0.6135,"max_v":0.6733,"avg_v":0.6388,"comp_len":3,"x":303.3007,"y":227.9221,"id":"mn104"},{"cover":6,"min_v":0.6096,"max_v":0.6414,"avg_v":0.6255,"comp_len":2,"x":337.8338,"y":210.8747,"id":"mn105"},{"cover":6,"min_v":0.6215,"max_v":0.6255,"avg_v":0.6235,"comp_len":2,"x":337.9048,"y":211.0345,"id":"mn106"},{"cover":6,"min_v":0.6892,"max_v":0.6892,"avg_v":0.6892,"comp_len":1,"x":337.2555,"y":209.6014,"id":"mn107"},{"cover":6,"min_v":0.6813,"max_v":0.6813,"avg_v":0.6813,"comp_len":1,"x":305.0221,"y":232.6516,"id":"mn108"},{"cover":6,"min_v":0.6574,"max_v":0.6574,"avg_v":0.6574,"comp_len":1,"x":260.0405,"y":326.265,"id":"mn109"},{"cover":6,"min_v":0.6653,"max_v":0.6773,"avg_v":0.6713,"comp_len":2,"x":367.2475,"y":183.8614,"id":"mn110"},{"cover":6,"min_v":0.6335,"max_v":0.6335,"avg_v":0.6335,"comp_len":1,"x":258.2821,"y":96.3769,"id":"mn111"},{"cover":6,"min_v":0.6972,"max_v":0.6972,"avg_v":0.6972,"comp_len":1,"x":389.4047,"y":409.1064,"id":"mn112"},{"cover":6,"min_v":0.6016,"max_v":0.6056,"avg_v":0.6036,"comp_len":2,"x":306.3248,"y":237.5131,"id":"mn113"},{"cover":6,"min_v":0.6534,"max_v":0.6853,"avg_v":0.6694,"comp_len":2,"x":337.3288,"y":209.7601,"id":"mn114"},{"cover":6,"min_v":0.6932,"max_v":0.6932,"avg_v":0.6932,"comp_len":1,"x":451.2807,"y":137.1261,"id":"mn115"},{"cover":6,"min_v":0.6175,"max_v":0.6494,"avg_v":0.6335,"comp_len":2,"x":337.9755,"y":211.1944,"id":"mn116"},{"cover":6,"min_v":0.6614,"max_v":0.6614,"avg_v":0.6614,"comp_len":1,"x":373.521,"y":196.485,"id":"mn117"},{"cover":6,"min_v":0.6375,"max_v":0.6375,"avg_v":0.6375,"comp_len":1,"x":355.8439,"y":204.0578,"id":"mn118"},{"cover":7,"min_v":0.7052,"max_v":0.7769,"avg_v":0.7397,"comp_len":3,"x":389.4753,"y":185.0748,"id":"mn119"},{"cover":7,"min_v":0.7928,"max_v":0.7928,"avg_v":0.7928,"comp_len":1,"x":389.2118,"y":409.2753,"id":"mn120"},{"cover":7,"min_v":0.753,"max_v":0.753,"avg_v":0.753,"comp_len":1,"x":255.5036,"y":154.0038,"id":"mn121"},{"cover":7,"min_v":0.7171,"max_v":0.7689,"avg_v":0.74,"comp_len":4,"x":355.5141,"y":203.3053,"id":"mn122"},{"cover":7,"min_v":0.7291,"max_v":0.7809,"avg_v":0.755,"comp_len":2,"x":354.6536,"y":201.4075,"id":"mn123"},{"cover":7,"min_v":0.761,"max_v":0.761,"avg_v":0.761,"comp_len":1,"x":372.7045,"y":194.6384,"id":"mn124"},{"cover":7,"min_v":0.7729,"max_v":0.7729,"avg_v":0.7729,"comp_len":1,"x":389.3083,"y":409.1909,"id":"mn125"},{"cover":7,"min_v":0.749,"max_v":0.749,"avg_v":0.749,"comp_len":1,"x":250.0,"y":269.2308,"id":"mn126"},{"cover":7,"min_v":0.7131,"max_v":0.7888,"avg_v":0.751,"comp_len":2,"x":424.3426,"y":168.8402,"id":"mn127"},{"cover":7,"min_v":0.7092,"max_v":0.7968,"avg_v":0.757,"comp_len":3,"x":417.7286,"y":155.9289,"id":"mn128"},{"cover":7,"min_v":0.7251,"max_v":0.7251,"avg_v":0.7251,"comp_len":1,"x":255.6273,"y":115.5023,"id":"mn129"},{"cover":7,"min_v":0.7211,"max_v":0.7211,"avg_v":0.7211,"comp_len":1,"x":254.4656,"y":115.4587,"id":"mn130"},{"cover":7,"min_v":0.7849,"max_v":0.7849,"avg_v":0.7849,"comp_len":1,"x":367.3676,"y":184.0746,"id":"mn131"},{"cover":7,"min_v":0.757,"max_v":0.757,"avg_v":0.757,"comp_len":1,"x":282.2286,"y":159.4082,"id":"mn132"},{"cover":7,"min_v":0.745,"max_v":0.745,"avg_v":0.745,"comp_len":1,"x":350.9583,"y":194.1338,"id":"mn133"},{"cover":7,"min_v":0.7012,"max_v":0.7012,"avg_v":0.7012,"comp_len":1,"x":414.7482,"y":438.0373,"id":"mn134"},{"cover":8,"min_v":0.8327,"max_v":0.8964,"avg_v":0.8705,"comp_len":6,"x":337.1819,"y":209.4429,"id":"mn135"},{"cover":8,"min_v":0.8048,"max_v":0.8526,"avg_v":0.8287,"comp_len":2,"x":256.133,"y":134.7785,"id":"mn136"},{"cover":8,"min_v":0.8486,"max_v":0.8486,"avg_v":0.8486,"comp_len":1,"x":406.9075,"y":176.9544,"id":"mn137"},{"cover":8,"min_v":0.8645,"max_v":0.8685,"avg_v":0.8665,"comp_len":2,"x":338.2554,"y":211.8352,"id":"mn138"},{"cover":8,"min_v":0.8805,"max_v":0.8805,"avg_v":0.8805,"comp_len":1,"x":250.0,"y":230.7692,"id":"mn139"},{"cover":8,"min_v":0.8167,"max_v":0.8884,"avg_v":0.8525,"comp_len":2,"x":296.8278,"y":311.0272,"id":"mn140"},{"cover":8,"min_v":0.8287,"max_v":0.8606,"avg_v":0.8486,"comp_len":3,"x":252.5165,"y":192.3626,"id":"mn141"},{"cover":8,"min_v":0.8127,"max_v":0.8367,"avg_v":0.8237,"comp_len":4,"x":350.5494,"y":193.4011,"id":"mn142"},{"cover":8,"min_v":0.8008,"max_v":0.8008,"avg_v":0.8008,"comp_len":1,"x":338.7581,"y":351.2092,"id":"mn143"},{"cover":8,"min_v":0.8088,"max_v":0.8088,"avg_v":0.8088,"comp_len":1,"x":258.3519,"y":96.3807,"id":"mn144"},{"cover":8,"min_v":0.8446,"max_v":0.8446,"avg_v":0.8446,"comp_len":1,"x":400.914,"y":165.2617,"id":"mn145"},{"cover":8,"min_v":0.8725,"max_v":0.8725,"avg_v":0.8725,"comp_len":1,"x":321.0677,"y":220.5628,"id":"mn146"},{"cover":9,"min_v":0.9004,"max_v":1.0,"avg_v":0.9493,"comp_len":14,"x":320.1814,"y":218.5083,"id":"mn147"},{"cover":9,"min_v":0.9124,"max_v":0.996,"avg_v":0.9522,"comp_len":9,"x":277.1964,"y":222.8036,"id":"mn148"},{"cover":9,"min_v":0.9203,"max_v":0.9801,"avg_v":0.9502,"comp_len":2,"x":355.8856,"y":204.1541,"id":"mn149"},{"cover":9,"min_v":0.9442,"max_v":0.9442,"avg_v":0.9442,"comp_len":1,"x":414.7311,"y":438.0523,"id":"mn150"}],"links":[{"value":1,"source":"mn0","target":"mn148"},{"value":1,"source":"mn0","target":"mn64"},{"value":1,"source":"mn0","target":"mn73"},{"value":1,"source":"mn0","target":"mn138"},{"value":2,"source":"mn1","target":"mn148"},{"value":2,"source":"mn1","target":"mn141"},{"value":4,"source":"mn2","target":"mn62"},{"value":3,"source":"mn2","target":"mn115"},{"value":2,"source":"mn2","target":"mn28"},{"value":2,"source":"mn3","target":"mn56"},{"value":2,"source":"mn3","target":"mn119"},{"value":3,"source":"mn4","target":"mn59"},{"value":1,"source":"mn4","target":"mn31"},{"value":1,"source":"mn5","target":"mn114"},{"value":1,"source":"mn5","target":"mn147"},{"value":2,"source":"mn5","target":"mn135"},{"value":1,"source":"mn6","target":"mn77"},{"value":6,"source":"mn6","target":"mn22"},{"value":2,"source":"mn7","target":"mn26"},{"value":3,"source":"mn7","target":"mn65"},{"value":4,"source":"mn7","target":"mn134"},{"value":1,"source":"mn7","target":"mn150"},{"value":1,"source":"mn7","target":"mn112"},{"value":1,"source":"mn8","target":"mn23"},{"value":1,"source":"mn8","target":"mn54"},{"value":1,"source":"mn8","target":"mn50"},{"value":1,"source":"mn8","target":"mn132"},{"value":3,"source":"mn9","target":"mn142"},{"value":1,"source":"mn9","target":"mn131"},{"value":1,"source":"mn10","target":"mn24"},{"value":1,"source":"mn10","target":"mn56"},{"value":2,"source":"mn10","target":"mn119"},{"value":2,"source":"mn11","target":"mn147"},{"value":1,"source":"mn11","target":"mn104"},{"value":1,"source":"mn11","target":"mn73"},{"value":1,"source":"mn12","target":"mn90"},{"value":2,"source":"mn12","target":"mn147"},{"value":1,"source":"mn12","target":"mn138"},{"value":2,"source":"mn13","target":"mn147"},{"value":1,"source":"mn13","target":"mn118"},{"value":1,"source":"mn13","target":"mn135"},{"value":2,"source":"mn14","target":"mn102"},{"value":2,"source":"mn14","target":"mn147"},{"value":3,"source":"mn15","target":"mn135"},{"value":1,"source":"mn15","target":"mn114"},{"value":1,"source":"mn16","target":"mn127"},{"value":1,"source":"mn16","target":"mn83"},{"value":2,"source":"mn16","target":"mn56"},{"value":2,"source":"mn17","target":"mn29"},{"value":2,"source":"mn17","target":"mn59"},{"value":2,"source":"mn18","target":"mn128"},{"value":1,"source":"mn18","target":"mn115"},{"value":1,"source":"mn18","target":"mn28"},{"value":3,"source":"mn19","target":"mn122"},{"value":1,"source":"mn19","target":"mn49"},{"value":2,"source":"mn19","target":"mn80"},{"value":1,"source":"mn19","target":"mn92"},{"value":1,"source":"mn19","target":"mn82"},{"value":1,"source":"mn20","target":"mn68"},{"value":1,"source":"mn20","target":"mn78"},{"value":1,"source":"mn20","target":"mn86"},{"value":1,"source":"mn20","target":"mn129"},{"value":1,"source":"mn20","target":"mn34"},{"value":1,"source":"mn21","target":"mn79"},{"value":2,"source":"mn21","target":"mn66"},{"value":1,"source":"mn21","target":"mn125"},{"value":2,"source":"mn21","target":"mn112"},{"value":1,"source":"mn21","target":"mn33"},{"value":1,"source":"mn21","target":"mn120"},{"value":2,"source":"mn22","target":"mn77"},{"value":2,"source":"mn22","target":"mn67"},{"value":4,"source":"mn22","target":"mn122"},{"value":2,"source":"mn23","target":"mn148"},{"value":1,"source":"mn23","target":"mn54"},{"value":1,"source":"mn23","target":"mn50"},{"value":3,"source":"mn24","target":"mn127"},{"value":3,"source":"mn24","target":"mn56"},{"value":3,"source":"mn24","target":"mn119"},{"value":1,"source":"mn24","target":"mn51"},{"value":1,"source":"mn25","target":"mn67"},{"value":2,"source":"mn25","target":"mn122"},{"value":1,"source":"mn25","target":"mn89"},{"value":1,"source":"mn25","target":"mn82"},{"value":1,"source":"mn26","target":"mn65"},{"value":1,"source":"mn26","target":"mn79"},{"value":1,"source":"mn26","target":"mn150"},{"value":1,"source":"mn27","target":"mn43"},{"value":1,"source":"mn27","target":"mn78"},{"value":1,"source":"mn27","target":"mn47"},{"value":2,"source":"mn27","target":"mn130"},{"value":2,"source":"mn27","target":"mn68"},{"value":1,"source":"mn27","target":"mn129"},{"value":2,"source":"mn28","target":"mn128"},{"value":2,"source":"mn28","target":"mn62"},{"value":1,"source":"mn28","target":"mn115"},{"value":1,"source":"mn29","target":"mn75"},{"value":5,"source":"mn29","target":"mn59"},{"value":2,"source":"mn30","target":"mn74"},{"value":1,"source":"mn30","target":"mn85"},{"value":1,"source":"mn30","target":"mn140"},{"value":1,"source":"mn30","target":"mn63"},{"value":1,"source":"mn31","target":"mn123"},{"value":3,"source":"mn31","target":"mn59"},{"value":2,"source":"mn32","target":"mn141"},{"value":2,"source":"mn32","target":"mn48"},{"value":1,"source":"mn32","target":"mn136"},{"value":1,"source":"mn32","target":"mn94"},{"value":1,"source":"mn32","target":"mn121"},{"value":1,"source":"mn32","target":"mn44"},{"value":1,"source":"mn33","target":"mn150"},{"value":1,"source":"mn33","target":"mn112"},{"value":1,"source":"mn33","target":"mn120"},{"value":1,"source":"mn33","target":"mn134"},{"value":1,"source":"mn34","target":"mn86"},{"value":1,"source":"mn34","target":"mn129"},{"value":1,"source":"mn34","target":"mn148"},{"value":1,"source":"mn34","target":"mn104"},{"value":1,"source":"mn35","target":"mn145"},{"value":1,"source":"mn35","target":"mn149"},{"value":2,"source":"mn35","target":"mn93"},{"value":2,"source":"mn35","target":"mn142"},{"value":2,"source":"mn35","target":"mn133"},{"value":1,"source":"mn36","target":"mn137"},{"value":1,"source":"mn36","target":"mn105"},{"value":3,"source":"mn36","target":"mn83"},{"value":1,"source":"mn37","target":"mn142"},{"value":1,"source":"mn37","target":"mn133"},{"value":1,"source":"mn37","target":"mn128"},{"value":2,"source":"mn37","target":"mn72"},{"value":1,"source":"mn38","target":"mn88"},{"value":2,"source":"mn38","target":"mn123"},{"value":1,"source":"mn38","target":"mn81"},{"value":1,"source":"mn38","target":"mn75"},{"value":1,"source":"mn39","target":"mn143"},{"value":1,"source":"mn39","target":"mn87"},{"value":1,"source":"mn39","target":"mn100"},{"value":2,"source":"mn39","target":"mn74"},{"value":1,"source":"mn40","target":"mn87"},{"value":2,"source":"mn40","target":"mn126"},{"value":1,"source":"mn40","target":"mn99"},{"value":1,"source":"mn40","target":"mn148"},{"value":1,"source":"mn40","target":"mn140"},{"value":2,"source":"mn40","target":"mn97"},{"value":1,"source":"mn41","target":"mn136"},{"value":1,"source":"mn41","target":"mn106"},{"value":1,"source":"mn41","target":"mn147"},{"value":1,"source":"mn41","target":"mn111"},{"value":1,"source":"mn41","target":"mn144"},{"value":2,"source":"mn42","target":"mn90"},{"value":1,"source":"mn42","target":"mn124"},{"value":1,"source":"mn42","target":"mn117"},{"value":1,"source":"mn42","target":"mn138"},{"value":1,"source":"mn43","target":"mn94"},{"value":1,"source":"mn43","target":"mn141"},{"value":1,"source":"mn43","target":"mn78"},{"value":1,"source":"mn43","target":"mn130"},{"value":1,"source":"mn44","target":"mn141"},{"value":1,"source":"mn44","target":"mn121"},{"value":1,"source":"mn44","target":"mn113"},{"value":1,"source":"mn44","target":"mn148"},{"value":1,"source":"mn45","target":"mn66"},{"value":1,"source":"mn45","target":"mn125"},{"value":1,"source":"mn45","target":"mn143"},{"value":1,"source":"mn45","target":"mn126"},{"value":1,"source":"mn45","target":"mn99"},{"value":1,"source":"mn46","target":"mn142"},{"value":1,"source":"mn46","target":"mn149"},{"value":2,"source":"mn46","target":"mn145"},{"value":2,"source":"mn46","target":"mn131"},{"value":2,"source":"mn46","target":"mn72"},{"value":1,"source":"mn47","target":"mn98"},{"value":1,"source":"mn47","target":"mn146"},{"value":1,"source":"mn47","target":"mn130"},{"value":1,"source":"mn47","target":"mn129"},{"value":1,"source":"mn48","target":"mn121"},{"value":2,"source":"mn48","target":"mn136"},{"value":1,"source":"mn49","target":"mn106"},{"value":1,"source":"mn49","target":"mn122"},{"value":1,"source":"mn49","target":"mn147"},{"value":1,"source":"mn49","target":"mn80"},{"value":1,"source":"mn50","target":"mn148"},{"value":1,"source":"mn50","target":"mn132"},{"value":1,"source":"mn50","target":"mn110"},{"value":1,"source":"mn51","target":"mn127"},{"value":1,"source":"mn51","target":"mn91"},{"value":1,"source":"mn51","target":"mn119"},{"value":1,"source":"mn51","target":"mn76"},{"value":1,"source":"mn52","target":"mn57"},{"value":1,"source":"mn52","target":"mn123"},{"value":1,"source":"mn52","target":"mn135"},{"value":1,"source":"mn52","target":"mn81"},{"value":1,"source":"mn52","target":"mn147"},{"value":2,"source":"mn53","target":"mn127"},{"value":2,"source":"mn53","target":"mn83"},{"value":1,"source":"mn53","target":"mn137"},{"value":2,"source":"mn54","target":"mn148"},{"value":1,"source":"mn54","target":"mn132"},{"value":3,"source":"mn55","target":"mn147"},{"value":2,"source":"mn55","target":"mn116"},{"value":1,"source":"mn56","target":"mn127"},{"value":1,"source":"mn56","target":"mn83"},{"value":2,"source":"mn56","target":"mn119"},{"value":3,"source":"mn57","target":"mn147"},{"value":1,"source":"mn57","target":"mn81"},{"value":1,"source":"mn58","target":"mn108"},{"value":2,"source":"mn58","target":"mn95"},{"value":1,"source":"mn58","target":"mn148"},{"value":1,"source":"mn58","target":"mn110"},{"value":6,"source":"mn59","target":"mn75"},{"value":1,"source":"mn59","target":"mn101"},{"value":2,"source":"mn59","target":"mn123"},{"value":1,"source":"mn60","target":"mn96"},{"value":3,"source":"mn60","target":"mn147"},{"value":1,"source":"mn60","target":"mn84"},{"value":2,"source":"mn61","target":"mn148"},{"value":1,"source":"mn61","target":"mn113"},{"value":1,"source":"mn61","target":"mn95"},{"value":1,"source":"mn61","target":"mn124"},{"value":2,"source":"mn62","target":"mn128"},{"value":3,"source":"mn62","target":"mn72"},{"value":1,"source":"mn62","target":"mn115"},{"value":1,"source":"mn63","target":"mn85"},{"value":2,"source":"mn63","target":"mn148"},{"value":1,"source":"mn63","target":"mn140"},{"value":2,"source":"mn64","target":"mn148"},{"value":1,"source":"mn64","target":"mn103"},{"value":1,"source":"mn64","target":"mn138"},{"value":1,"source":"mn65","target":"mn79"},{"value":1,"source":"mn65","target":"mn112"},{"value":1,"source":"mn66","target":"mn125"},{"value":1,"source":"mn66","target":"mn143"},{"value":1,"source":"mn66","target":"mn120"},{"value":3,"source":"mn67","target":"mn122"},{"value":2,"source":"mn68","target":"mn78"},{"value":1,"source":"mn68","target":"mn129"},{"value":2,"source":"mn69","target":"mn148"},{"value":1,"source":"mn69","target":"mn132"},{"value":1,"source":"mn69","target":"mn142"},{"value":1,"source":"mn69","target":"mn103"},{"value":1,"source":"mn70","target":"mn141"},{"value":2,"source":"mn70","target":"mn148"},{"value":1,"source":"mn70","target":"mn78"},{"value":1,"source":"mn70","target":"mn86"},{"value":3,"source":"mn71","target":"mn148"},{"value":1,"source":"mn71","target":"mn87"},{"value":1,"source":"mn71","target":"mn139"},{"value":1,"source":"mn72","target":"mn145"},{"value":1,"source":"mn72","target":"mn131"},{"value":1,"source":"mn72","target":"mn142"},{"value":2,"source":"mn72","target":"mn133"},{"value":6,"source":"mn72","target":"mn128"},{"value":1,"source":"mn73","target":"mn148"},{"value":1,"source":"mn73","target":"mn104"},{"value":1,"source":"mn73","target":"mn147"},{"value":1,"source":"mn73","target":"mn138"},{"value":1,"source":"mn74","target":"mn87"},{"value":1,"source":"mn74","target":"mn100"},{"value":1,"source":"mn74","target":"mn139"},{"value":2,"source":"mn74","target":"mn140"},{"value":1,"source":"mn74","target":"mn85"},{"value":1,"source":"mn75","target":"mn135"},{"value":2,"source":"mn75","target":"mn88"},{"value":2,"source":"mn75","target":"mn101"},{"value":1,"source":"mn75","target":"mn123"},{"value":3,"source":"mn76","target":"mn91"},{"value":2,"source":"mn76","target":"mn119"},{"value":3,"source":"mn77","target":"mn122"},{"value":3,"source":"mn78","target":"mn141"},{"value":1,"source":"mn78","target":"mn86"},{"value":1,"source":"mn79","target":"mn125"},{"value":1,"source":"mn79","target":"mn150"},{"value":1,"source":"mn79","target":"mn112"},{"value":1,"source":"mn80","target":"mn147"},{"value":1,"source":"mn80","target":"mn92"},{"value":1,"source":"mn80","target":"mn107"},{"value":1,"source":"mn81","target":"mn147"},{"value":1,"source":"mn81","target":"mn88"},{"value":1,"source":"mn81","target":"mn123"},{"value":1,"source":"mn82","target":"mn89"},{"value":1,"source":"mn82","target":"mn144"},{"value":1,"source":"mn82","target":"mn122"},{"value":1,"source":"mn82","target":"mn92"},{"value":1,"source":"mn83","target":"mn127"},{"value":3,"source":"mn83","target":"mn119"},{"value":1,"source":"mn83","target":"mn137"},{"value":2,"source":"mn83","target":"mn105"},{"value":3,"source":"mn83","target":"mn91"},{"value":1,"source":"mn83","target":"mn135"},{"value":2,"source":"mn84","target":"mn113"},{"value":1,"source":"mn84","target":"mn96"},{"value":1,"source":"mn84","target":"mn90"},{"value":1,"source":"mn84","target":"mn147"},{"value":1,"source":"mn85","target":"mn139"},{"value":2,"source":"mn85","target":"mn148"},{"value":2,"source":"mn86","target":"mn148"},{"value":1,"source":"mn87","target":"mn143"},{"value":2,"source":"mn87","target":"mn126"},{"value":2,"source":"mn87","target":"mn139"},{"value":1,"source":"mn87","target":"mn148"},{"value":1,"source":"mn88","target":"mn147"},{"value":1,"source":"mn88","target":"mn135"},{"value":2,"source":"mn89","target":"mn106"},{"value":1,"source":"mn89","target":"mn122"},{"value":1,"source":"mn89","target":"mn144"},{"value":1,"source":"mn90","target":"mn113"},{"value":1,"source":"mn90","target":"mn124"},{"value":3,"source":"mn90","target":"mn147"},{"value":1,"source":"mn90","target":"mn138"},{"value":1,"source":"mn91","target":"mn127"},{"value":1,"source":"mn91","target":"mn118"},{"value":5,"source":"mn91","target":"mn135"},{"value":2,"source":"mn91","target":"mn119"},{"value":1,"source":"mn92","target":"mn144"},{"value":1,"source":"mn92","target":"mn107"},{"value":1,"source":"mn92","target":"mn147"},{"value":2,"source":"mn93","target":"mn103"},{"value":1,"source":"mn93","target":"mn149"},{"value":1,"source":"mn93","target":"mn142"},{"value":2,"source":"mn94","target":"mn141"},{"value":1,"source":"mn94","target":"mn136"},{"value":1,"source":"mn94","target":"mn130"},{"value":1,"source":"mn95","target":"mn148"},{"value":1,"source":"mn95","target":"mn108"},{"value":2,"source":"mn95","target":"mn124"},{"value":1,"source":"mn95","target":"mn110"},{"value":1,"source":"mn95","target":"mn117"},{"value":1,"source":"mn95","target":"mn149"},{"value":1,"source":"mn96","target":"mn121"},{"value":1,"source":"mn96","target":"mn113"},{"value":1,"source":"mn96","target":"mn111"},{"value":1,"source":"mn96","target":"mn147"},{"value":1,"source":"mn97","target":"mn148"},{"value":2,"source":"mn97","target":"mn140"},{"value":1,"source":"mn97","target":"mn108"},{"value":2,"source":"mn98","target":"mn116"},{"value":1,"source":"mn98","target":"mn136"},{"value":1,"source":"mn98","target":"mn146"},{"value":1,"source":"mn98","target":"mn130"},{"value":1,"source":"mn99","target":"mn125"},{"value":1,"source":"mn99","target":"mn126"},{"value":1,"source":"mn99","target":"mn109"},{"value":1,"source":"mn99","target":"mn140"},{"value":1,"source":"mn100","target":"mn143"},{"value":1,"source":"mn100","target":"mn120"},{"value":1,"source":"mn100","target":"mn109"},{"value":1,"source":"mn100","target":"mn140"},{"value":1,"source":"mn101","target":"mn135"},{"value":2,"source":"mn101","target":"mn123"},{"value":3,"source":"mn102","target":"mn147"},{"value":2,"source":"mn102","target":"mn105"},{"value":1,"source":"mn102","target":"mn104"},{"value":2,"source":"mn102","target":"mn135"},{"value":2,"source":"mn103","target":"mn142"},{"value":2,"source":"mn103","target":"mn148"},{"value":1,"source":"mn103","target":"mn149"},{"value":1,"source":"mn103","target":"mn138"},{"value":2,"source":"mn104","target":"mn146"},{"value":3,"source":"mn104","target":"mn147"},{"value":1,"source":"mn104","target":"mn129"},{"value":2,"source":"mn104","target":"mn148"},{"value":3,"source":"mn105","target":"mn147"},{"value":1,"source":"mn105","target":"mn137"},{"value":1,"source":"mn105","target":"mn135"},{"value":2,"source":"mn106","target":"mn122"},{"value":3,"source":"mn106","target":"mn147"},{"value":1,"source":"mn106","target":"mn144"},{"value":4,"source":"mn107","target":"mn147"},{"value":2,"source":"mn108","target":"mn148"},{"value":1,"source":"mn108","target":"mn140"},{"value":1,"source":"mn109","target":"mn125"},{"value":1,"source":"mn109","target":"mn150"},{"value":1,"source":"mn109","target":"mn120"},{"value":1,"source":"mn109","target":"mn140"},{"value":2,"source":"mn110","target":"mn148"},{"value":1,"source":"mn110","target":"mn132"},{"value":3,"source":"mn110","target":"mn142"},{"value":1,"source":"mn110","target":"mn149"},{"value":1,"source":"mn111","target":"mn121"},{"value":1,"source":"mn111","target":"mn136"},{"value":1,"source":"mn111","target":"mn144"},{"value":1,"source":"mn111","target":"mn147"},{"value":1,"source":"mn112","target":"mn134"},{"value":1,"source":"mn113","target":"mn121"},{"value":2,"source":"mn113","target":"mn148"},{"value":1,"source":"mn113","target":"mn124"},{"value":4,"source":"mn114","target":"mn147"},{"value":4,"source":"mn114","target":"mn135"},{"value":1,"source":"mn115","target":"mn128"},{"value":2,"source":"mn116","target":"mn136"},{"value":3,"source":"mn116","target":"mn147"},{"value":1,"source":"mn116","target":"mn146"},{"value":1,"source":"mn117","target":"mn124"},{"value":2,"source":"mn117","target":"mn149"},{"value":1,"source":"mn117","target":"mn138"},{"value":1,"source":"mn118","target":"mn127"},{"value":1,"source":"mn118","target":"mn147"},{"value":1,"source":"mn118","target":"mn137"},{"value":1,"source":"mn118","target":"mn135"},{"value":1,"source":"mn120","target":"mn143"},{"value":1,"source":"mn120","target":"mn150"},{"value":1,"source":"mn121","target":"mn136"},{"value":2,"source":"mn123","target":"mn135"},{"value":1,"source":"mn125","target":"mn150"},{"value":1,"source":"mn126","target":"mn143"},{"value":1,"source":"mn127","target":"mn137"},{"value":1,"source":"mn128","target":"mn142"},{"value":1,"source":"mn129","target":"mn146"},{"value":1,"source":"mn130","target":"mn136"},{"value":3,"source":"mn131","target":"mn142"},{"value":1,"source":"mn132","target":"mn148"},{"value":1,"source":"mn132","target":"mn142"},{"value":1,"source":"mn133","target":"mn145"},{"value":1,"source":"mn133","target":"mn142"},{"value":1,"source":"mn134","target":"mn150"},{"value":6,"source":"mn135","target":"mn147"},{"value":1,"source":"mn136","target":"mn147"},{"value":1,"source":"mn137","target":"mn147"},{"value":2,"source":"mn138","target":"mn149"},{"value":2,"source":"mn138","target":"mn147"},{"value":2,"source":"mn139","target":"mn148"},{"value":1,"source":"mn140","target":"mn148"},{"value":5,"source":"mn141","target":"mn148"},{"value":1,"source":"mn142","target":"mn149"},{"value":1,"source":"mn144","target":"mn147"},{"value":2,"source":"mn145","target":"mn149"},{"value":1,"source":"mn146","target":"mn147"}],"info":{"component_method":"connected_components","link_method":"connectivity","cover_overlap":0.0,"cover_intervals":10,"cover":[{"level":0,"range":[0.0,0.1]},{"level":1,"range":[0.1,0.2]},{"level":2,"range":[0.2,0.3]},{"level":3,"range":[0.3,0.4]},{"level":4,"range":[0.4,0.5]},{"level":5,"range":[0.5,0.6]},{"level":6,"range":[0.6,0.7]},{"level":7,"range":[0.7,0.8]},{"level":8,"range":[0.8,0.9]},{"level":9,"range":[0.9,1.0]}],"compute_time":0.0139}}