{"nodes":[{"cover":0,"min_v":0.1685,"max_v":0.1685,"avg_v":0.1685,"comp_len":1,"x":197.4217,"y":216.2099,"id":"mn0"},{"cover":0,"min_v":0.0112,"max_v":0.2255,"avg_v":0.1189,"comp_len":3,"x":185.4503,"y":357.0436,"id":"mn1"},{"cover":0,"min_v":0.0,"max_v":0.221,"avg_v":0.1415,"comp_len":3,"x":279.1667,"y":305.2771,"id":"mn2"},{"cover":0,"min_v":0.0951,"max_v":0.0951,"avg_v":0.0951,"comp_len":1,"x":371.1904,"y":219.375,"id":"mn3"},{"cover":0,"min_v":0.1831,"max_v":0.2003,"avg_v":0.1928,"comp_len":4,"x":312.3981,"y":253.5681,"id":"mn4"},{"cover":0,"min_v":0.0834,"max_v":0.1896,"avg_v":0.151,"comp_len":3,"x":311.5846,"y":260.6576,"id":"mn5"},{"cover":0,"min_v":0.1763,"max_v":0.1763,"avg_v":0.1763,"comp_len":1,"x":201.6161,"y":289.5633,"id":"mn6"},{"cover":0,"min_v":0.1355,"max_v":0.247,"avg_v":0.2197,"comp_len":5,"x":309.9683,"y":267.6083,"id":"mn7"},{"cover":0,"min_v":0.1211,"max_v":0.248,"avg_v":0.1867,"comp_len":4,"x":304.4216,"y":280.7333,"id":"mn8"},{"cover":0,"min_v":0.1888,"max_v":0.1888,"avg_v":0.1888,"comp_len":1,"x":197.4217,"y":283.7901,"id":"mn9"},{"cover":0,"min_v":0.1696,"max_v":0.179,"avg_v":0.1743,"comp_len":2,"x":258.8947,"y":311.8638,"id":"mn10"},{"cover":0,"min_v":0.1702,"max_v":0.1702,"avg_v":0.1702,"comp_len":1,"x":201.6161,"y":210.4367,"id":"mn11"},{"cover":0,"min_v":0.1861,"max_v":0.1861,"avg_v":0.1861,"comp_len":1,"x":206.4414,"y":205.1793,"id":"mn12"},{"cover":0,"min_v":0.205,"max_v":0.2108,"avg_v":0.2079,"comp_len":2,"x":251.7848,"y":312.4745,"id":"mn13"},{"cover":0,"min_v":0.1468,"max_v":0.1487,"avg_v":0.1475,"comp_len":3,"x":244.6516,"y":312.2707,"id":"mn14"},{"cover":0,"min_v":0.0132,"max_v":0.2235,"avg_v":0.1221,"comp_len":3,"x":193.9126,"y":277.5763,"id":"mn15"},{"cover":0,"min_v":0.1148,"max_v":0.2254,"avg_v":0.1873,"comp_len":3,"x":368.509,"y":210.2429,"id":"mn16"},{"cover":0,"min_v":0.1877,"max_v":0.1877,"avg_v":0.1877,"comp_len":1,"x":211.8345,"y":200.5061,"id":"mn17"},{"cover":0,"min_v":0.1695,"max_v":0.1789,"avg_v":0.1749,"comp_len":3,"x":307.5702,"y":274.3294,"id":"mn18"},{"cover":0,"min_v":0.0076,"max_v":0.1261,"avg_v":0.0805,"comp_len":3,"x":117.8567,"y":462.222,"id":"mn19"},{"cover":0,"min_v":0.2026,"max_v":0.2026,"avg_v":0.2026,"comp_len":1,"x":191.1347,"y":271.0031,"id":"mn20"},{"cover":0,"min_v":0.0952,"max_v":0.2045,"avg_v":0.1498,"comp_len":2,"x":272.6755,"y":308.2415,"id":"mn21"},{"cover":0,"min_v":0.0166,"max_v":0.2349,"avg_v":0.126,"comp_len":3,"x":160.3585,"y":337.1172,"id":"mn22"},{"cover":0,"min_v":0.1713,"max_v":0.1713,"avg_v":0.1713,"comp_len":1,"x":189.1243,"y":264.156,"id":"mn23"},{"cover":0,"min_v":0.1888,"max_v":0.1888,"avg_v":0.1888,"comp_len":1,"x":290.9288,"y":202.7657,"id":"mn24"},{"cover":0,"min_v":0.1084,"max_v":0.2257,"avg_v":0.1849,"comp_len":3,"x":237.5881,"y":311.2552,"id":"mn25"},{"cover":0,"min_v":0.197,"max_v":0.2031,"avg_v":0.1999,"comp_len":3,"x":265.8886,"y":310.4467,"id":"mn26"},{"cover":0,"min_v":0.0929,"max_v":0.1964,"avg_v":0.1447,"comp_len":2,"x":187.9074,"y":257.1245,"id":"mn27"},{"cover":0,"min_v":0.202,"max_v":0.218,"avg_v":0.2113,"comp_len":3,"x":300.5636,"y":286.7366,"id":"mn28"},{"cover":0,"min_v":0.1232,"max_v":0.1279,"avg_v":0.1256,"comp_len":3,"x":217.7252,"y":196.4782,"id":"mn29"},{"cover":0,"min_v":0.0811,"max_v":0.0811,"avg_v":0.0811,"comp_len":1,"x":224.0366,"y":193.148,"id":"mn30"},{"cover":0,"min_v":0.0887,"max_v":0.0887,"avg_v":0.0887,"comp_len":1,"x":181.4219,"y":354.5086,"id":"mn31"},{"cover":0,"min_v":0.1753,"max_v":0.1753,"avg_v":0.1753,"comp_len":1,"x":187.5,"y":250.0,"id":"mn32"},{"cover":0,"min_v":0.2111,"max_v":0.2111,"avg_v":0.2111,"comp_len":1,"x":486.4441,"y":168.7955,"id":"mn33"},{"cover":0,"min_v":0.1957,"max_v":0.1957,"avg_v":0.1957,"comp_len":1,"x":187.9074,"y":242.8755,"id":"mn34"},{"cover":0,"min_v":0.0193,"max_v":0.2453,"avg_v":0.1565,"comp_len":4,"x":317.5801,"y":144.8433,"id":"mn35"},{"cover":0,"min_v":0.0809,"max_v":0.0809,"avg_v":0.0809,"comp_len":1,"x":296.0463,"y":207.7391,"id":"mn36"},{"cover":0,"min_v":0.1758,"max_v":0.1849,"avg_v":0.1804,"comp_len":2,"x":230.6864,"y":309.441,"id":"mn37"},{"cover":0,"min_v":0.0988,"max_v":0.0988,"avg_v":0.0988,"comp_len":1,"x":230.6864,"y":190.559,"id":"mn38"},{"cover":0,"min_v":0.1706,"max_v":0.1706,"avg_v":0.1706,"comp_len":1,"x":237.5881,"y":188.7448,"id":"mn39"},{"cover":0,"min_v":0.1753,"max_v":0.1753,"avg_v":0.1753,"comp_len":1,"x":244.6516,"y":187.7293,"id":"mn40"},{"cover":0,"min_v":0.1873,"max_v":0.1873,"avg_v":0.1873,"comp_len":1,"x":312.3981,"y":246.4319,"id":"mn41"},{"cover":0,"min_v":0.1911,"max_v":0.1911,"avg_v":0.1911,"comp_len":1,"x":251.7848,"y":187.5255,"id":"mn42"},{"cover":0,"min_v":0.1331,"max_v":0.1347,"avg_v":0.1339,"comp_len":2,"x":486.828,"y":169.9219,"id":"mn43"},{"cover":0,"min_v":0.2355,"max_v":0.2422,"avg_v":0.2389,"comp_len":2,"x":485.6604,"y":166.5483,"id":"mn44"},{"cover":0,"min_v":0.1794,"max_v":0.1794,"avg_v":0.1794,"comp_len":1,"x":258.8947,"y":188.1362,"id":"mn45"},{"cover":0,"min_v":0.1782,"max_v":0.181,"avg_v":0.1796,"comp_len":2,"x":296.0463,"y":292.2609,"id":"mn46"},{"cover":0,"min_v":0.1696,"max_v":0.1696,"avg_v":0.1696,"comp_len":1,"x":265.8886,"y":189.5533,"id":"mn47"},{"cover":0,"min_v":0.0896,"max_v":0.0896,"avg_v":0.0896,"comp_len":1,"x":300.5636,"y":213.2634,"id":"mn48"},{"cover":0,"min_v":0.0117,"max_v":0.0117,"avg_v":0.0117,"comp_len":1,"x":304.4216,"y":219.2667,"id":"mn49"},{"cover":0,"min_v":0.0831,"max_v":0.0831,"avg_v":0.0831,"comp_len":1,"x":307.5702,"y":225.6706,"id":"mn50"},{"cover":0,"min_v":0.1706,"max_v":0.1706,"avg_v":0.1706,"comp_len":1,"x":189.1243,"y":235.844,"id":"mn51"},{"cover":1,"min_v":0.2564,"max_v":0.3645,"avg_v":0.3301,"comp_len":8,"x":427.1877,"y":188.6748,"id":"mn52"},{"cover":1,"min_v":0.2625,"max_v":0.4926,"avg_v":0.3548,"comp_len":126,"x":250.0,"y":250.0,"id":"mn53"},{"cover":1,"min_v":0.2555,"max_v":0.2555,"avg_v":0.2555,"comp_len":1,"x":368.8821,"y":288.6271,"id":"mn54"},{"cover":2,"min_v":0.6285,"max_v":0.6285,"avg_v":0.6285,"comp_len":1,"x":224.0366,"y":306.852,"id":"mn55"},{"cover":2,"min_v":0.7081,"max_v":0.7081,"avg_v":0.7081,"comp_len":1,"x":191.1347,"y":228.9969,"id":"mn56"},{"cover":2,"min_v":0.5871,"max_v":0.5871,"avg_v":0.5871,"comp_len":1,"x":285.2777,"y":301.592,"id":"mn57"},{"cover":2,"min_v":0.5285,"max_v":0.6357,"avg_v":0.5821,"comp_len":2,"x":217.7252,"y":303.5218,"id":"mn58"},{"cover":2,"min_v":0.5367,"max_v":0.5479,"avg_v":0.5423,"comp_len":2,"x":206.4414,"y":294.8207,"id":"mn59"},{"cover":2,"min_v":0.5594,"max_v":0.6409,"avg_v":0.6001,"comp_len":2,"x":309.9683,"y":232.3917,"id":"mn60"},{"cover":2,"min_v":0.6208,"max_v":0.6208,"avg_v":0.6208,"comp_len":1,"x":272.6755,"y":191.7585,"id":"mn61"},{"cover":2,"min_v":0.6446,"max_v":0.6446,"avg_v":0.6446,"comp_len":1,"x":279.1667,"y":194.7229,"id":"mn62"},{"cover":2,"min_v":0.5761,"max_v":0.5761,"avg_v":0.5761,"comp_len":1,"x":211.8345,"y":299.4939,"id":"mn63"},{"cover":2,"min_v":0.5688,"max_v":0.5688,"avg_v":0.5688,"comp_len":1,"x":290.9288,"y":297.2343,"id":"mn64"},{"cover":2,"min_v":0.5148,"max_v":0.5148,"avg_v":0.5148,"comp_len":1,"x":311.5846,"y":239.3424,"id":"mn65"},{"cover":2,"min_v":0.5712,"max_v":0.5712,"avg_v":0.5712,"comp_len":1,"x":193.9126,"y":222.4237,"id":"mn66"},{"cover":2,"min_v":0.6731,"max_v":0.6731,"avg_v":0.6731,"comp_len":1,"x":136.296,"y":301.9269,"id":"mn67"},{"cover":3,"min_v":1.0,"max_v":1.0,"avg_v":1.0,"comp_len":1,"x":151.6513,"y":409.6364,"id":"mn68"},{"cover":3,"min_v":0.8976,"max_v":0.8976,"avg_v":0.8976,"comp_len":1,"x":285.2777,"y":198.408,"id":"mn69"}],"links":[{"value":4,"source":"mn0","target":"mn53"},{"value":1,"source":"mn0","target":"mn66"},{"value":3,"source":"mn1","target":"mn58"},{"value":3,"source":"mn1","target":"mn68"},{"value":7,"source":"mn2","target":"mn53"},{"value":2,"source":"mn2","target":"mn69"},{"value":1,"source":"mn3","target":"mn60"},{"value":1,"source":"mn3","target":"mn52"},{"value":1,"source":"mn3","target":"mn65"},{"value":1,"source":"mn3","target":"mn53"},{"value":12,"source":"mn4","target":"mn53"},{"value":10,"source":"mn5","target":"mn53"},{"value":5,"source":"mn6","target":"mn53"},{"value":9,"source":"mn7","target":"mn53"},{"value":5,"source":"mn7","target":"mn54"},{"value":8,"source":"mn8","target":"mn53"},{"value":5,"source":"mn9","target":"mn53"},{"value":6,"source":"mn10","target":"mn53"},{"value":2,"source":"mn10","target":"mn66"},{"value":4,"source":"mn11","target":"mn53"},{"value":1,"source":"mn11","target":"mn66"},{"value":4,"source":"mn12","target":"mn53"},{"value":1,"source":"mn12","target":"mn59"},{"value":6,"source":"mn13","target":"mn53"},{"value":2,"source":"mn13","target":"mn56"},{"value":6,"source":"mn14","target":"mn53"},{"value":5,"source":"mn15","target":"mn53"},{"value":3,"source":"mn15","target":"mn67"},{"value":6,"source":"mn16","target":"mn52"},{"value":4,"source":"mn16","target":"mn60"},{"value":1,"source":"mn17","target":"mn58"},{"value":4,"source":"mn17","target":"mn53"},{"value":9,"source":"mn18","target":"mn53"},{"value":2,"source":"mn18","target":"mn63"},{"value":1,"source":"mn19","target":"mn58"},{"value":3,"source":"mn19","target":"mn68"},{"value":3,"source":"mn19","target":"mn53"},{"value":5,"source":"mn20","target":"mn53"},{"value":7,"source":"mn21","target":"mn53"},{"value":1,"source":"mn22","target":"mn53"},{"value":5,"source":"mn22","target":"mn59"},{"value":5,"source":"mn23","target":"mn53"},{"value":1,"source":"mn24","target":"mn68"},{"value":1,"source":"mn24","target":"mn62"},{"value":3,"source":"mn24","target":"mn53"},{"value":6,"source":"mn25","target":"mn53"},{"value":2,"source":"mn25","target":"mn55"},{"value":7,"source":"mn26","target":"mn53"},{"value":2,"source":"mn26","target":"mn61"},{"value":2,"source":"mn27","target":"mn61"},{"value":5,"source":"mn27","target":"mn53"},{"value":8,"source":"mn28","target":"mn53"},{"value":3,"source":"mn28","target":"mn67"},{"value":2,"source":"mn29","target":"mn62"},{"value":4,"source":"mn29","target":"mn53"},{"value":4,"source":"mn30","target":"mn53"},{"value":2,"source":"mn31","target":"mn58"},{"value":2,"source":"mn31","target":"mn53"},{"value":5,"source":"mn32","target":"mn53"},{"value":4,"source":"mn33","target":"mn52"},{"value":1,"source":"mn33","target":"mn65"},{"value":5,"source":"mn34","target":"mn53"},{"value":1,"source":"mn35","target":"mn59"},{"value":2,"source":"mn35","target":"mn53"},{"value":4,"source":"mn35","target":"mn69"},{"value":3,"source":"mn36","target":"mn53"},{"value":1,"source":"mn36","target":"mn61"},{"value":2,"source":"mn37","target":"mn56"},{"value":6,"source":"mn37","target":"mn53"},{"value":4,"source":"mn38","target":"mn53"},{"value":4,"source":"mn39","target":"mn53"},{"value":1,"source":"mn39","target":"mn63"},{"value":4,"source":"mn40","target":"mn53"},{"value":1,"source":"mn40","target":"mn57"},{"value":1,"source":"mn41","target":"mn52"},{"value":1,"source":"mn41","target":"mn60"},{"value":2,"source":"mn41","target":"mn53"},{"value":1,"source":"mn41","target":"mn65"},{"value":1,"source":"mn42","target":"mn62"},{"value":4,"source":"mn42","target":"mn53"},{"value":4,"source":"mn43","target":"mn52"},{"value":2,"source":"mn43","target":"mn60"},{"value":8,"source":"mn44","target":"mn52"},{"value":4,"source":"mn45","target":"mn53"},{"value":1,"source":"mn45","target":"mn56"},{"value":8,"source":"mn46","target":"mn53"},{"value":4,"source":"mn47","target":"mn53"},{"value":1,"source":"mn47","target":"mn64"},{"value":3,"source":"mn48","target":"mn53"},{"value":1,"source":"mn48","target":"mn55"},{"value":3,"source":"mn49","target":"mn53"},{"value":1,"source":"mn50","target":"mn60"},{"value":3,"source":"mn50","target":"mn53"},{"value":5,"source":"mn51","target":"mn53"},{"value":3,"source":"mn52","target":"mn60"},{"value":2,"source":"mn52","target":"mn65"},{"value":3,"source":"mn53","target":"mn60"},{"value":8,"source":"mn53","target":"mn64"},{"value":3,"source":"mn53","target":"mn65"},{"value":6,"source":"mn53","target":"mn55"},{"value":8,"source":"mn53","target":"mn57"},{"value":3,"source":"mn53","target":"mn67"},{"value":5,"source":"mn53","target":"mn56"},{"value":4,"source":"mn53","target":"mn61"},{"value":6,"source":"mn53","target":"mn58"},{"value":2,"source":"mn53","target":"mn68"},{"value":4,"source":"mn53","target":"mn62"},{"value":5,"source":"mn53","target":"mn66"},{"value":6,"source":"mn53","target":"mn63"},{"value":6,"source":"mn53","target":"mn59"},{"value":4,"source":"mn53","target":"mn69"},{"value":2,"source":"mn58","target":"mn68"},{"value":1,"source":"mn59","target":"mn69"},{"value":1,"source":"mn62","target":"mn68"}],"info":{"component_method":"connected_components","link_method":"connectivity","cover_overlap":0.0,"cover_intervals":4,"cover":[{"level":0,"range":[0.0,0.25]},{"level":1,"range":[0.25,0.5]},{"level":2,"range":[0.5,0.75]},{"level":3,"range":[0.75,1.0]}],"compute_time":0.0296}}