{"nodes":[{"cover":0,"min_v":0.2452,"max_v":0.2493,"avg_v":0.2472,"comp_len":3,"x":425.5586,"y":354.9668,"id":"mn0"},{"cover":0,"min_v":0.0363,"max_v":0.2407,"avg_v":0.1713,"comp_len":3,"x":343.2085,"y":93.891,"id":"mn1"},{"cover":0,"min_v":0.0414,"max_v":0.2408,"avg_v":0.169,"comp_len":3,"x":318.5251,"y":132.1045,"id":"mn2"},{"cover":0,"min_v":0.2202,"max_v":0.2275,"avg_v":0.2246,"comp_len":3,"x":406.0483,"y":343.3101,"id":"mn3"},{"cover":0,"min_v":0.1987,"max_v":0.2107,"avg_v":0.2061,"comp_len":3,"x":250.0,"y":250.0,"id":"mn4"},{"cover":0,"min_v":0.2298,"max_v":0.248,"avg_v":0.2402,"comp_len":3,"x":405.9832,"y":343.4189,"id":"mn5"},{"cover":0,"min_v":0.0419,"max_v":0.2265,"avg_v":0.1649,"comp_len":3,"x":320.0624,"y":133.0115,"id":"mn6"},{"cover":0,"min_v":0.1833,"max_v":0.2018,"avg_v":0.193,"comp_len":3,"x":445.0623,"y":366.6344,"id":"mn7"},{"cover":0,"min_v":0.0225,"max_v":0.232,"avg_v":0.0935,"comp_len":3,"x":343.2841,"y":93.9362,"id":"mn8"},{"cover":0,"min_v":0.0401,"max_v":0.2481,"avg_v":0.1734,"comp_len":3,"x":318.3878,"y":132.0248,"id":"mn9"},{"cover":0,"min_v":0.199,"max_v":0.1998,"avg_v":0.1994,"comp_len":2,"x":326.4044,"y":299.2629,"id":"mn10"},{"cover":0,"min_v":0.0133,"max_v":0.2066,"avg_v":0.11,"comp_len":2,"x":289.7144,"y":305.4214,"id":"mn11"},{"cover":0,"min_v":0.1958,"max_v":0.2076,"avg_v":0.2017,"comp_len":2,"x":367.0267,"y":319.9986,"id":"mn12"},{"cover":0,"min_v":0.2046,"max_v":0.206,"avg_v":0.2053,"comp_len":2,"x":367.122,"y":319.8389,"id":"mn13"},{"cover":0,"min_v":0.2051,"max_v":0.2084,"avg_v":0.2067,"comp_len":2,"x":324.3259,"y":302.3462,"id":"mn14"},{"cover":0,"min_v":0.1785,"max_v":0.183,"avg_v":0.1807,"comp_len":2,"x":347.416,"y":308.5093,"id":"mn15"},{"cover":0,"min_v":0.2044,"max_v":0.21,"avg_v":0.2072,"comp_len":2,"x":425.5518,"y":354.9782,"id":"mn16"},{"cover":0,"min_v":0.2164,"max_v":0.2314,"avg_v":0.2239,"comp_len":2,"x":406.0398,"y":343.3243,"id":"mn17"},{"cover":0,"min_v":0.2126,"max_v":0.2192,"avg_v":0.2159,"comp_len":2,"x":366.5283,"y":54.8743,"id":"mn18"},{"cover":0,"min_v":0.2111,"max_v":0.2372,"avg_v":0.2242,"comp_len":2,"x":302.1433,"y":175.5316,"id":"mn19"},{"cover":0,"min_v":0.1929,"max_v":0.1929,"avg_v":0.1929,"comp_len":1,"x":378.2624,"y":35.4103,"id":"mn20"},{"cover":0,"min_v":0.2162,"max_v":0.2162,"avg_v":0.2162,"comp_len":1,"x":308.8101,"y":152.7653,"id":"mn21"},{"cover":0,"min_v":0.1858,"max_v":0.1858,"avg_v":0.1858,"comp_len":1,"x":307.1821,"y":212.8655,"id":"mn22"},{"cover":0,"min_v":0.2034,"max_v":0.2034,"avg_v":0.2034,"comp_len":1,"x":425.5505,"y":354.9803,"id":"mn23"},{"cover":0,"min_v":0.0334,"max_v":0.0334,"avg_v":0.0334,"comp_len":1,"x":309.9375,"y":153.4561,"id":"mn24"},{"cover":0,"min_v":0.0617,"max_v":0.0617,"avg_v":0.0617,"comp_len":1,"x":309.3748,"y":153.1091,"id":"mn25"},{"cover":0,"min_v":0.2101,"max_v":0.2101,"avg_v":0.2101,"comp_len":1,"x":367.0775,"y":319.9134,"id":"mn26"},{"cover":0,"min_v":0.1976,"max_v":0.1976,"avg_v":0.1976,"comp_len":1,"x":323.4595,"y":303.5553,"id":"mn27"},{"cover":0,"min_v":0.1869,"max_v":0.1869,"avg_v":0.1869,"comp_len":1,"x":325.8625,"y":300.0934,"id":"mn28"},{"cover":0,"min_v":0.1934,"max_v":0.1934,"avg_v":0.1934,"comp_len":1,"x":343.322,"y":93.9588,"id":"mn29"},{"cover":0,"min_v":0.0029,"max_v":0.0029,"avg_v":0.0029,"comp_len":1,"x":302.7053,"y":293.2541,"id":"mn30"},{"cover":0,"min_v":0.2035,"max_v":0.2035,"avg_v":0.2035,"comp_len":1,"x":330.319,"y":112.6728,"id":"mn31"},{"cover":0,"min_v":0.2115,"max_v":0.2115,"avg_v":0.2115,"comp_len":1,"x":367.0012,"y":320.0411,"id":"mn32"},{"cover":0,"min_v":0.037,"max_v":0.037,"avg_v":0.037,"comp_len":1,"x":405.9776,"y":343.4283,"id":"mn33"},{"cover":0,"min_v":0.2174,"max_v":0.2174,"avg_v":0.2174,"comp_len":1,"x":366.9757,"y":320.0837,"id":"mn34"},{"cover":0,"min_v":0.2066,"max_v":0.2066,"avg_v":0.2066,"comp_len":1,"x":425.5499,"y":354.9814,"id":"mn35"},{"cover":0,"min_v":0.1885,"max_v":0.1885,"avg_v":0.1885,"comp_len":1,"x":292.9082,"y":197.0128,"id":"mn36"},{"cover":0,"min_v":0.1905,"max_v":0.1905,"avg_v":0.1905,"comp_len":1,"x":310.7504,"y":219.0461,"id":"mn37"},{"cover":0,"min_v":0.0,"max_v":0.0,"avg_v":0.0,"comp_len":1,"x":315.9431,"y":187.4223,"id":"mn38"},{"cover":0,"min_v":0.1788,"max_v":0.1788,"avg_v":0.1788,"comp_len":1,"x":215.1798,"y":220.7824,"id":"mn39"},{"cover":0,"min_v":0.1884,"max_v":0.1884,"avg_v":0.1884,"comp_len":1,"x":299.7635,"y":296.6086,"id":"mn40"},{"cover":0,"min_v":0.0269,"max_v":0.0269,"avg_v":0.0269,"comp_len":1,"x":330.2125,"y":112.6105,"id":"mn41"},{"cover":0,"min_v":0.1905,"max_v":0.1905,"avg_v":0.1905,"comp_len":1,"x":296.6086,"y":299.7635,"id":"mn42"},{"cover":0,"min_v":0.1858,"max_v":0.1858,"avg_v":0.1858,"comp_len":1,"x":318.0884,"y":246.4316,"id":"mn43"},{"cover":0,"min_v":0.0175,"max_v":0.0175,"avg_v":0.0175,"comp_len":1,"x":406.037,"y":343.3291,"id":"mn44"},{"cover":0,"min_v":0.2026,"max_v":0.2026,"avg_v":0.2026,"comp_len":1,"x":445.0627,"y":366.6337,"id":"mn45"},{"cover":0,"min_v":0.2069,"max_v":0.2069,"avg_v":0.2069,"comp_len":1,"x":405.9719,"y":343.4378,"id":"mn46"},{"cover":0,"min_v":0.2361,"max_v":0.2361,"avg_v":0.2361,"comp_len":1,"x":405.9804,"y":343.4236,"id":"mn47"},{"cover":0,"min_v":0.201,"max_v":0.201,"avg_v":0.201,"comp_len":1,"x":326.9372,"y":298.4265,"id":"mn48"},{"cover":0,"min_v":0.019,"max_v":0.019,"avg_v":0.019,"comp_len":1,"x":425.5138,"y":355.0417,"id":"mn49"},{"cover":0,"min_v":0.1955,"max_v":0.1955,"avg_v":0.1955,"comp_len":1,"x":286.0046,"y":307.9001,"id":"mn50"},{"cover":0,"min_v":0.1987,"max_v":0.1987,"avg_v":0.1987,"comp_len":1,"x":322.5734,"y":304.75,"id":"mn51"},{"cover":1,"min_v":0.2593,"max_v":0.4455,"avg_v":0.393,"comp_len":15,"x":296.8216,"y":172.0757,"id":"mn52"},{"cover":1,"min_v":0.3417,"max_v":0.4011,"avg_v":0.3824,"comp_len":11,"x":307.9001,"y":286.0046,"id":"mn53"},{"cover":1,"min_v":0.2582,"max_v":0.4441,"avg_v":0.4065,"comp_len":11,"x":406.0511,"y":343.3054,"id":"mn54"},{"cover":1,"min_v":0.377,"max_v":0.3858,"avg_v":0.3805,"comp_len":10,"x":289.3648,"y":227.2727,"id":"mn55"},{"cover":1,"min_v":0.3832,"max_v":0.4108,"avg_v":0.4016,"comp_len":8,"x":347.5222,"y":308.3321,"id":"mn56"},{"cover":1,"min_v":0.3834,"max_v":0.3998,"avg_v":0.3917,"comp_len":8,"x":305.4214,"y":289.7144,"id":"mn57"},{"cover":1,"min_v":0.3785,"max_v":0.3949,"avg_v":0.3871,"comp_len":7,"x":261.3636,"y":269.6824,"id":"mn58"},{"cover":1,"min_v":0.4289,"max_v":0.4573,"avg_v":0.4425,"comp_len":6,"x":386.4791,"y":331.7519,"id":"mn59"},{"cover":1,"min_v":0.3936,"max_v":0.4106,"avg_v":0.4015,"comp_len":5,"x":406.0455,"y":343.3149,"id":"mn60"},{"cover":1,"min_v":0.3479,"max_v":0.3924,"avg_v":0.3753,"comp_len":4,"x":347.6281,"y":308.1547,"id":"mn61"},{"cover":1,"min_v":0.4002,"max_v":0.4068,"avg_v":0.4046,"comp_len":4,"x":386.5088,"y":331.7022,"id":"mn62"},{"cover":1,"min_v":0.4139,"max_v":0.4363,"avg_v":0.4235,"comp_len":3,"x":318.7992,"y":132.2642,"id":"mn63"},{"cover":1,"min_v":0.4031,"max_v":0.4318,"avg_v":0.4174,"comp_len":2,"x":354.8702,"y":74.3837,"id":"mn64"},{"cover":1,"min_v":0.3634,"max_v":0.3875,"avg_v":0.3755,"comp_len":2,"x":204.5455,"y":250.0,"id":"mn65"},{"cover":1,"min_v":0.4009,"max_v":0.4037,"avg_v":0.4023,"comp_len":2,"x":366.5993,"y":54.9167,"id":"mn66"},{"cover":1,"min_v":0.375,"max_v":0.375,"avg_v":0.375,"comp_len":1,"x":347.2026,"y":308.8632,"id":"mn67"},{"cover":1,"min_v":0.3922,"max_v":0.3922,"avg_v":0.3922,"comp_len":1,"x":318.6622,"y":132.1843,"id":"mn68"},{"cover":1,"min_v":0.4391,"max_v":0.4391,"avg_v":0.4391,"comp_len":1,"x":331.7395,"y":113.5134,"id":"mn69"},{"cover":2,"min_v":0.5737,"max_v":0.5919,"avg_v":0.5826,"comp_len":11,"x":282.1412,"y":282.1412,"id":"mn70"},{"cover":2,"min_v":0.5805,"max_v":0.6226,"avg_v":0.6039,"comp_len":8,"x":386.5385,"y":331.6526,"id":"mn71"},{"cover":2,"min_v":0.5973,"max_v":0.6664,"avg_v":0.6235,"comp_len":7,"x":307.1042,"y":151.7537,"id":"mn72"},{"cover":2,"min_v":0.5394,"max_v":0.7443,"avg_v":0.609,"comp_len":6,"x":327.9753,"y":296.7366,"id":"mn73"},{"cover":2,"min_v":0.5666,"max_v":0.6125,"avg_v":0.5808,"comp_len":4,"x":287.1345,"y":192.8179,"id":"mn74"},{"cover":2,"min_v":0.5723,"max_v":0.6182,"avg_v":0.5855,"comp_len":4,"x":425.5564,"y":354.9704,"id":"mn75"},{"cover":2,"min_v":0.6121,"max_v":0.6204,"avg_v":0.6165,"comp_len":3,"x":354.934,"y":74.4218,"id":"mn76"},{"cover":2,"min_v":0.5783,"max_v":0.6169,"avg_v":0.5976,"comp_len":2,"x":308.2435,"y":152.4248,"id":"mn77"},{"cover":2,"min_v":0.5819,"max_v":0.5849,"avg_v":0.5834,"comp_len":2,"x":327.4609,"y":297.5844,"id":"mn78"},{"cover":2,"min_v":0.6014,"max_v":0.6297,"avg_v":0.6156,"comp_len":2,"x":406.0143,"y":343.3669,"id":"mn79"},{"cover":2,"min_v":0.5806,"max_v":0.5806,"avg_v":0.5806,"comp_len":1,"x":261.3636,"y":230.3176,"id":"mn80"},{"cover":2,"min_v":0.586,"max_v":0.586,"avg_v":0.586,"comp_len":1,"x":313.6532,"y":225.5658,"id":"mn81"},{"cover":2,"min_v":0.5812,"max_v":0.5812,"avg_v":0.5812,"comp_len":1,"x":302.9872,"y":207.0918,"id":"mn82"},{"cover":2,"min_v":0.5581,"max_v":0.5581,"avg_v":0.5581,"comp_len":1,"x":261.7645,"y":293.9057,"id":"mn83"},{"cover":2,"min_v":0.5789,"max_v":0.5789,"avg_v":0.5789,"comp_len":1,"x":298.2118,"y":201.7882,"id":"mn84"},{"cover":2,"min_v":0.6174,"max_v":0.6174,"avg_v":0.6174,"comp_len":1,"x":425.4803,"y":355.0976,"id":"mn85"},{"cover":2,"min_v":0.6413,"max_v":0.6413,"avg_v":0.6413,"comp_len":1,"x":315.1791,"y":156.9145,"id":"mn86"},{"cover":2,"min_v":0.5978,"max_v":0.5978,"avg_v":0.5978,"comp_len":1,"x":425.5511,"y":354.9792,"id":"mn87"},{"cover":3,"min_v":0.8035,"max_v":1.0,"avg_v":0.8778,"comp_len":3,"x":331.6071,"y":113.4343,"id":"mn88"},{"cover":3,"min_v":0.7574,"max_v":0.7698,"avg_v":0.7636,"comp_len":2,"x":227.2727,"y":250.0,"id":"mn89"},{"cover":3,"min_v":0.7983,"max_v":0.7983,"avg_v":0.7983,"comp_len":1,"x":464.5684,"y":378.298,"id":"mn90"},{"cover":3,"min_v":0.7989,"max_v":0.7989,"avg_v":0.7989,"comp_len":1,"x":316.2578,"y":157.6792,"id":"mn91"},{"cover":3,"min_v":0.7613,"max_v":0.7613,"avg_v":0.7613,"comp_len":1,"x":333.4457,"y":172.8636,"id":"mn92"},{"cover":3,"min_v":0.9611,"max_v":0.9611,"avg_v":0.9611,"comp_len":1,"x":317.3424,"y":239.334,"id":"mn93"},{"cover":3,"min_v":0.909,"max_v":0.909,"avg_v":0.909,"comp_len":1,"x":347.3095,"y":308.6864,"id":"mn94"},{"cover":3,"min_v":0.7737,"max_v":0.7737,"avg_v":0.7737,"comp_len":1,"x":238.2355,"y":293.9057,"id":"mn95"},{"cover":3,"min_v":0.8028,"max_v":0.8028,"avg_v":0.8028,"comp_len":1,"x":405.9691,"y":343.4425,"id":"mn96"}],"links":[{"value":2,"source":"mn0","target":"mn75"},{"value":9,"source":"mn0","target":"mn54"},{"value":1,"source":"mn1","target":"mn76"},{"value":3,"source":"mn1","target":"mn64"},{"value":4,"source":"mn1","target":"mn88"},{"value":3,"source":"mn2","target":"mn52"},{"value":4,"source":"mn2","target":"mn72"},{"value":2,"source":"mn2","target":"mn77"},{"value":1,"source":"mn2","target":"mn69"},{"value":5,"source":"mn3","target":"mn54"},{"value":6,"source":"mn3","target":"mn71"},{"value":2,"source":"mn4","target":"mn80"},{"value":3,"source":"mn4","target":"mn89"},{"value":4,"source":"mn4","target":"mn58"},{"value":1,"source":"mn5","target":"mn62"},{"value":1,"source":"mn5","target":"mn79"},{"value":7,"source":"mn5","target":"mn59"},{"value":2,"source":"mn5","target":"mn85"},{"value":1,"source":"mn6","target":"mn72"},{"value":2,"source":"mn6","target":"mn77"},{"value":3,"source":"mn6","target":"mn69"},{"value":4,"source":"mn6","target":"mn88"},{"value":1,"source":"mn7","target":"mn60"},{"value":2,"source":"mn7","target":"mn75"},{"value":2,"source":"mn7","target":"mn73"},{"value":1,"source":"mn7","target":"mn94"},{"value":2,"source":"mn7","target":"mn90"},{"value":1,"source":"mn7","target":"mn67"},{"value":1,"source":"mn8","target":"mn63"},{"value":3,"source":"mn8","target":"mn88"},{"value":5,"source":"mn8","target":"mn76"},{"value":6,"source":"mn9","target":"mn72"},{"value":4,"source":"mn9","target":"mn52"},{"value":2,"source":"mn10","target":"mn70"},{"value":2,"source":"mn10","target":"mn61"},{"value":3,"source":"mn10","target":"mn53"},{"value":1,"source":"mn10","target":"mn73"},{"value":1,"source":"mn11","target":"mn58"},{"value":1,"source":"mn11","target":"mn89"},{"value":2,"source":"mn11","target":"mn70"},{"value":2,"source":"mn11","target":"mn65"},{"value":1,"source":"mn11","target":"mn95"},{"value":1,"source":"mn12","target":"mn73"},{"value":4,"source":"mn12","target":"mn71"},{"value":3,"source":"mn12","target":"mn56"},{"value":3,"source":"mn13","target":"mn61"},{"value":1,"source":"mn13","target":"mn70"},{"value":2,"source":"mn13","target":"mn53"},{"value":2,"source":"mn13","target":"mn78"},{"value":3,"source":"mn14","target":"mn57"},{"value":3,"source":"mn14","target":"mn70"},{"value":2,"source":"mn14","target":"mn53"},{"value":1,"source":"mn15","target":"mn75"},{"value":1,"source":"mn15","target":"mn94"},{"value":3,"source":"mn15","target":"mn73"},{"value":2,"source":"mn15","target":"mn54"},{"value":1,"source":"mn15","target":"mn71"},{"value":3,"source":"mn16","target":"mn60"},{"value":3,"source":"mn16","target":"mn75"},{"value":1,"source":"mn16","target":"mn54"},{"value":1,"source":"mn16","target":"mn71"},{"value":4,"source":"mn17","target":"mn71"},{"value":4,"source":"mn17","target":"mn54"},{"value":2,"source":"mn18","target":"mn76"},{"value":2,"source":"mn18","target":"mn66"},{"value":3,"source":"mn18","target":"mn64"},{"value":1,"source":"mn18","target":"mn93"},{"value":2,"source":"mn19","target":"mn52"},{"value":3,"source":"mn19","target":"mn74"},{"value":2,"source":"mn19","target":"mn86"},{"value":1,"source":"mn19","target":"mn91"},{"value":1,"source":"mn20","target":"mn81"},{"value":2,"source":"mn20","target":"mn66"},{"value":1,"source":"mn20","target":"mn55"},{"value":1,"source":"mn20","target":"mn93"},{"value":3,"source":"mn21","target":"mn52"},{"value":2,"source":"mn21","target":"mn72"},{"value":2,"source":"mn22","target":"mn55"},{"value":1,"source":"mn22","target":"mn82"},{"value":1,"source":"mn22","target":"mn52"},{"value":1,"source":"mn22","target":"mn93"},{"value":2,"source":"mn23","target":"mn60"},{"value":1,"source":"mn23","target":"mn79"},{"value":1,"source":"mn23","target":"mn87"},{"value":1,"source":"mn23","target":"mn62"},{"value":1,"source":"mn24","target":"mn52"},{"value":1,"source":"mn24","target":"mn86"},{"value":1,"source":"mn24","target":"mn63"},{"value":1,"source":"mn24","target":"mn72"},{"value":3,"source":"mn25","target":"mn52"},{"value":1,"source":"mn25","target":"mn72"},{"value":5,"source":"mn26","target":"mn56"},{"value":3,"source":"mn27","target":"mn57"},{"value":2,"source":"mn27","target":"mn70"},{"value":2,"source":"mn28","target":"mn53"},{"value":1,"source":"mn28","target":"mn61"},{"value":1,"source":"mn28","target":"mn73"},{"value":1,"source":"mn28","target":"mn78"},{"value":1,"source":"mn29","target":"mn68"},{"value":2,"source":"mn29","target":"mn88"},{"value":2,"source":"mn29","target":"mn72"},{"value":4,"source":"mn30","target":"mn70"},{"value":1,"source":"mn31","target":"mn63"},{"value":1,"source":"mn31","target":"mn91"},{"value":1,"source":"mn31","target":"mn81"},{"value":1,"source":"mn31","target":"mn66"},{"value":1,"source":"mn31","target":"mn76"},{"value":2,"source":"mn32","target":"mn62"},{"value":1,"source":"mn32","target":"mn71"},{"value":2,"source":"mn32","target":"mn56"},{"value":3,"source":"mn33","target":"mn59"},{"value":1,"source":"mn33","target":"mn96"},{"value":1,"source":"mn34","target":"mn96"},{"value":2,"source":"mn34","target":"mn59"},{"value":2,"source":"mn34","target":"mn56"},{"value":1,"source":"mn35","target":"mn87"},{"value":2,"source":"mn35","target":"mn60"},{"value":1,"source":"mn35","target":"mn62"},{"value":1,"source":"mn35","target":"mn71"},{"value":4,"source":"mn36","target":"mn55"},{"value":1,"source":"mn36","target":"mn89"},{"value":1,"source":"mn37","target":"mn74"},{"value":1,"source":"mn37","target":"mn91"},{"value":1,"source":"mn37","target":"mn81"},{"value":2,"source":"mn37","target":"mn55"},{"value":1,"source":"mn38","target":"mn84"},{"value":1,"source":"mn38","target":"mn92"},{"value":1,"source":"mn38","target":"mn82"},{"value":1,"source":"mn38","target":"mn55"},{"value":1,"source":"mn39","target":"mn89"},{"value":1,"source":"mn39","target":"mn55"},{"value":1,"source":"mn39","target":"mn92"},{"value":1,"source":"mn39","target":"mn65"},{"value":1,"source":"mn39","target":"mn82"},{"value":4,"source":"mn40","target":"mn70"},{"value":1,"source":"mn40","target":"mn57"},{"value":1,"source":"mn41","target":"mn86"},{"value":2,"source":"mn41","target":"mn63"},{"value":1,"source":"mn41","target":"mn91"},{"value":3,"source":"mn42","target":"mn70"},{"value":2,"source":"mn42","target":"mn53"},{"value":1,"source":"mn43","target":"mn55"},{"value":1,"source":"mn43","target":"mn80"},{"value":1,"source":"mn43","target":"mn58"},{"value":1,"source":"mn43","target":"mn84"},{"value":1,"source":"mn43","target":"mn92"},{"value":3,"source":"mn44","target":"mn71"},{"value":1,"source":"mn44","target":"mn60"},{"value":3,"source":"mn45","target":"mn75"},{"value":2,"source":"mn45","target":"mn54"},{"value":2,"source":"mn46","target":"mn59"},{"value":1,"source":"mn46","target":"mn90"},{"value":1,"source":"mn46","target":"mn67"},{"value":1,"source":"mn46","target":"mn96"},{"value":4,"source":"mn47","target":"mn59"},{"value":1,"source":"mn47","target":"mn79"},{"value":4,"source":"mn48","target":"mn53"},{"value":1,"source":"mn48","target":"mn78"},{"value":2,"source":"mn49","target":"mn79"},{"value":1,"source":"mn49","target":"mn59"},{"value":1,"source":"mn49","target":"mn90"},{"value":2,"source":"mn50","target":"mn70"},{"value":2,"source":"mn50","target":"mn58"},{"value":1,"source":"mn50","target":"mn57"},{"value":3,"source":"mn51","target":"mn57"},{"value":1,"source":"mn51","target":"mn58"},{"value":1,"source":"mn51","target":"mn95"},{"value":9,"source":"mn52","target":"mn72"},{"value":9,"source":"mn52","target":"mn74"},{"value":1,"source":"mn52","target":"mn86"},{"value":1,"source":"mn52","target":"mn55"},{"value":4,"source":"mn52","target":"mn77"},{"value":1,"source":"mn52","target":"mn93"},{"value":9,"source":"mn53","target":"mn73"},{"value":13,"source":"mn53","target":"mn70"},{"value":7,"source":"mn53","target":"mn78"},{"value":6,"source":"mn54","target":"mn75"},{"value":8,"source":"mn54","target":"mn71"},{"value":6,"source":"mn55","target":"mn74"},{"value":2,"source":"mn55","target":"mn81"},{"value":2,"source":"mn55","target":"mn80"},{"value":4,"source":"mn55","target":"mn84"},{"value":2,"source":"mn55","target":"mn89"},{"value":3,"source":"mn55","target":"mn82"},{"value":2,"source":"mn55","target":"mn93"},{"value":4,"source":"mn56","target":"mn73"},{"value":1,"source":"mn56","target":"mn62"},{"value":1,"source":"mn56","target":"mn96"},{"value":3,"source":"mn56","target":"mn71"},{"value":1,"source":"mn56","target":"mn59"},{"value":2,"source":"mn56","target":"mn85"},{"value":13,"source":"mn57","target":"mn70"},{"value":1,"source":"mn57","target":"mn58"},{"value":1,"source":"mn57","target":"mn95"},{"value":1,"source":"mn58","target":"mn80"},{"value":3,"source":"mn58","target":"mn70"},{"value":2,"source":"mn58","target":"mn89"},{"value":3,"source":"mn58","target":"mn83"},{"value":2,"source":"mn58","target":"mn95"},{"value":1,"source":"mn58","target":"mn92"},{"value":1,"source":"mn59","target":"mn90"},{"value":2,"source":"mn59","target":"mn79"},{"value":2,"source":"mn59","target":"mn96"},{"value":1,"source":"mn59","target":"mn85"},{"value":2,"source":"mn60","target":"mn75"},{"value":3,"source":"mn60","target":"mn87"},{"value":1,"source":"mn60","target":"mn79"},{"value":1,"source":"mn60","target":"mn90"},{"value":6,"source":"mn60","target":"mn71"},{"value":6,"source":"mn61","target":"mn73"},{"value":1,"source":"mn61","target":"mn94"},{"value":2,"source":"mn61","target":"mn70"},{"value":1,"source":"mn61","target":"mn78"},{"value":3,"source":"mn62","target":"mn79"},{"value":2,"source":"mn62","target":"mn87"},{"value":2,"source":"mn62","target":"mn85"},{"value":1,"source":"mn62","target":"mn71"},{"value":1,"source":"mn63","target":"mn86"},{"value":2,"source":"mn63","target":"mn72"},{"value":1,"source":"mn63","target":"mn91"},{"value":2,"source":"mn63","target":"mn76"},{"value":1,"source":"mn63","target":"mn88"},{"value":1,"source":"mn64","target":"mn76"},{"value":1,"source":"mn64","target":"mn93"},{"value":1,"source":"mn64","target":"mn77"},{"value":1,"source":"mn64","target":"mn88"},{"value":3,"source":"mn65","target":"mn89"},{"value":1,"source":"mn65","target":"mn95"},{"value":2,"source":"mn65","target":"mn83"},{"value":1,"source":"mn65","target":"mn92"},{"value":1,"source":"mn66","target":"mn81"},{"value":3,"source":"mn66","target":"mn76"},{"value":1,"source":"mn66","target":"mn93"},{"value":1,"source":"mn67","target":"mn90"},{"value":2,"source":"mn67","target":"mn73"},{"value":1,"source":"mn67","target":"mn96"},{"value":4,"source":"mn68","target":"mn72"},{"value":1,"source":"mn68","target":"mn88"},{"value":1,"source":"mn69","target":"mn72"},{"value":1,"source":"mn69","target":"mn77"},{"value":1,"source":"mn70","target":"mn95"},{"value":1,"source":"mn71","target":"mn73"},{"value":2,"source":"mn72","target":"mn88"},{"value":3,"source":"mn73","target":"mn94"},{"value":1,"source":"mn73","target":"mn96"},{"value":1,"source":"mn74","target":"mn91"},{"value":3,"source":"mn75","target":"mn94"},{"value":2,"source":"mn76","target":"mn88"},{"value":1,"source":"mn77","target":"mn93"},{"value":1,"source":"mn77","target":"mn88"},{"value":1,"source":"mn79","target":"mn90"},{"value":1,"source":"mn80","target":"mn89"},{"value":1,"source":"mn81","target":"mn91"},{"value":1,"source":"mn82","target":"mn92"},{"value":1,"source":"mn83","target":"mn95"},{"value":1,"source":"mn83","target":"mn92"},{"value":1,"source":"mn84","target":"mn92"},{"value":1,"source":"mn86","target":"mn91"}],"info":{"component_method":"modularity","link_method":"connectivity","cover_overlap":0.0,"cover_intervals":4,"cover":[{"level":0,"range":[0.0,0.25]},{"level":1,"range":[0.25,0.5]},{"level":2,"range":[0.5,0.75]},{"level":3,"range":[0.75,1.0]}],"compute_time":0.0624}}